Workbook

Sheet FESTIVALS_MASTER
A1: IDENTITY | C1: LOCATION | H1: TIME | L1: DIGITAL PRESENCE | S1: ORGANIZATION | Y1: CULTURAL DOMAINS | AE1: ACCESSIBILITY & SUSTAINABILITY | AH1: METADATA
A2: festival_id | B2: festival_name | C2: city_name | D2: city_geonames_id | E2: region | F2: region_nuts | G2: country_iso | H2: first_edition_year | I2: festival_status | J2: duration_days | K2: recurrence | L2: website_official | M2: website_secondary | N2: website_active | O2: website_languages | P2: instagram | Q2: facebook | R2: digital_presence_score | S2: organizer_type | T2: has_documented_public_funding | U2: has_international_call | V2: has_international_partners | W2: has_international_orientation | X2: has_photography | Y2: has_other_visual_arts | Z2: has_books_press | AA2: has_heritage | AB2: has_architecture_design | AC2: has_performing_arts | AD2: has_audiovisual_multimedia | AE2: venue_type | AF2: ticket_policy | AG2: sustainability_claim | AH2: notes | AI2: record_last_updated
A3: FEST000002 | B3: ANALOGICA | C3: Bolzano | D3: {=XLOOKUP(C3,Locations!A:A,Locations!D:D,"")} -> 3181913 | E3: {=XLOOKUP(C3,Locations!A:A,Locations!E:E,"")} -> Trentino-Alto Adige/Südtirol | F3: {=XLOOKUP(C3,Locations!A:A,Locations!F:F,"")} -> ITH1 | G3: IT | H3: 2011 | I3: active | J3: 5 | K3: annual | L3: https://www.analogica.org/ | M3: null | N3: 1 | O3: IT_EN | P3: https://www.instagram.com/_analogica_/ | Q3: null | R3: {=IF(A3:A6981="","",IF(L3:L6981<>"null",2,0)+IF(N3:N6981=1,2,0)+IF(O3:O6981="IT_EN",1,0)+IF(O3:O6981="MULTI",2,0)+IF(P3:P6981<>"null",2,0)+IF(Q3:Q6981<>"null",2,0))} -> 7 | S3: non-profit | T3: 1 | U3: 1 | V3: 1 | W3: 1 | X3: 1 | Y3: 0 | Z3: 0 | AA3: 1 | AB3: 0 | AC3: 1 | AD3: 1 | AE3: cultural_space | AF3: unknown | AG3: 0 | AI3: 46227
A4: FEST000003 | B4: Milano Centrale Festival | C4: Milano | D4: {=XLOOKUP(C4,Locations!A:A,Locations!D:D,"")} -> 6951411 | E4: {=XLOOKUP(C4,Locations!A:A,Locations!E:E,"")} -> Lombardia | F4: {=XLOOKUP(C4,Locations!A:A,Locations!F:F,"")} -> ITC4 | G4: IT | H4: 2023 | I4: active | J4: 3 | K4: annual | L4: https://www.centralefestival.com/milano2026.html | M4: null | N4: 1 | O4: IT_ONLY | P4: https://www.instagram.com/centralefestival/ | Q4: https://facebook.com/centralefestival/ | R4: 8 | S4: private | T4: 0 | U4: 0 | V4: 0 | W4: 0 | X4: 1 | Y4: 1 | Z4: 1 | AA4: 0 | AB4: 0 | AC4: 1 | AD4: 1 | AE4: mixed | AF4: free | AG4: 0 | AI4: 46227
A5: FEST000004 | B5: Fano Centrale Festival | C5: Fano | D5: {=XLOOKUP(C5,Locations!A:A,Locations!D:D,"")} -> 3177219 | E5: {=XLOOKUP(C5,Locations!A:A,Locations!E:E,"")} -> Marche | F5: {=XLOOKUP(C5,Locations!A:A,Locations!F:F,"")} -> ITI3 | G5: IT | H5: 2009 | I5: active | J5: 7 | K5: annual | L5: https://www.centralefestival.com/fano2027.html | M5: null | N5: 1 | O5: IT_ONLY | P5: https://www.instagram.com/centralefestival/ | Q5: https://facebook.com/centralefestival/ | R5: 8 | S5: non-profit | T5: 1 | U5: 1 | V5: 0 | W5: 1 | X5: 1 | Y5: 1 | Z5: 1 | AA5: 0 | AB5: 0 | AC5: 0 | AD5: 1 | AE5: mixed | AF5: free | AG5: 0 | AI5: 46227
A6: FEST000005 | B6: Festival della Fotografia Etica | C6: Lodi | D6: {=XLOOKUP(C6,Locations!A:A,Locations!D:D,"")} -> 3174638 | E6: {=XLOOKUP(C6,Locations!A:A,Locations!E:E,"")} -> Lombardia | F6: {=XLOOKUP(C6,Locations!A:A,Locations!F:F,"")} -> ITC4 | G6: IT | H6: 2010 | I6: active | J6: 30 | K6: annual | L6: https://www.festivaldellafotografiaetica.it/ | M6: null | N6: 1 | O6: IT_EN | P6: https://www.instagram.com/fotografiaetica/ | Q6: https://www.facebook.com/Festival.della.Fotografia.Etica/ | R6: 9 | S6: non-profit | T6: 1 | U6: 1 | V6: 1 | W6: 1 | X6: 1 | Y6: 0 | Z6: 1 | AA6: 0 | AB6: 0 | AC6: 0 | AD6: 1 | AE6: mixed | AF6: paid | AG6: 1 | AI6: 46227
A7: FEST000006 | B7: Siena Awards Photo Festival | C7: Siena | D7: {=XLOOKUP(C7,Locations!A:A,Locations!D:D,"")} -> 3166548 | E7: {=XLOOKUP(C7,Locations!A:A,Locations!E:E,"")} -> Toscana | F7: {=XLOOKUP(C7,Locations!A:A,Locations!F:F,"")} -> ITI1 | G7: IT | H7: 2015 | I7: active | J7: 51 | K7: annual | L7: https://www.sienawards.com/it/festival | M7: null | N7: 1 | O7: IT_EN | P7: https://www.instagram.com/sienawards/ | Q7: https://www.facebook.com/sipacontest | R7: 9 | S7: non-profit | T7: 0 | U7: 1 | V7: 1 | W7: 1 | X7: 1 | Y7: 0 | Z7: 1 | AA7: 0 | AB7: 0 | AC7: 0 | AD7: 0 | AE7: mixed | AF7: paid | AG7: 0 | AI7: 46227
A8: FEST000008 | B8: Yeast Photo Festival | C8: Matino | D8: {=XLOOKUP(C8,Locations!A:A,Locations!D:D,"")} -> 3173711 | E8: {=XLOOKUP(C8,Locations!A:A,Locations!E:E,"")} -> Puglia | F8: {=XLOOKUP(C8,Locations!A:A,Locations!F:F,"")} -> ITF4 | G8: IT | H8: 2021 | I8: active | J8: 59 | K8: annual | L8: https://www.yeastphotofestival.it/ | M8: null | N8: 1 | O8: IT_EN | P8: https://www.instagram.com/yeastphotofestival/ | Q8: https://www.facebook.com/yeastphotofestival/ | R8: 9 | S8: non-profit | T8: 0 | U8: 1 | V8: 1 | W8: 1 | X8: 1 | Y8: 1 | Z8: 0 | AA8: 0 | AB8: 0 | AC8: 0 | AD8: 0 | AE8: mixed | AF8: unknown | AG8: 1 | AH8: Festival diffuso sul territorio (Salento) | AI8: 46227
A9: FEST000009 | B9: Grenze - Arsenali Fotografici | C9: Verona | D9: {=XLOOKUP(C9,Locations!A:A,Locations!D:D,"")} -> 3164527 | E9: {=XLOOKUP(C9,Locations!A:A,Locations!E:E,"")} -> Veneto | F9: {=XLOOKUP(C9,Locations!A:A,Locations!F:F,"")} -> ITH3 | G9: IT | H9: 2018 | I9: active | J9: 32 | K9: annual | L9: https://www.grenzearsenalifotografici.com/ | M9: null | N9: 1 | O9: IT_EN | P9: https://www.instagram.com/grenze.arsenali.fotografici/?hl=it | Q9: https://www.facebook.com/grenzearsenalifotografici/ | R9: 9 | S9: non-profit | T9: 1 | U9: 1 | V9: 1 | W9: 1 | X9: 1 | Y9: 1 | Z9: 1 | AA9: 0 | AB9: 0 | AC9: 1 | AD9: 0 | AE9: mixed | AF9: unknown | AG9: 0 | AI9: 46227
A10: FEST000011 | B10: SI Fest - Savignano Immagini Festival | C10: Savignano sul Rubicone | D10: {=XLOOKUP(C10,Locations!A:A,Locations!D:D,"")} -> 3167030 | E10: {=XLOOKUP(C10,Locations!A:A,Locations!E:E,"")} -> Emilia-Romagna | F10: {=XLOOKUP(C10,Locations!A:A,Locations!F:F,"")} -> ITH5 | G10: IT | H10: 1992 | I10: active | J10: 17 | K10: annual | L10: https://www.sifest.it/ | M10: null | N10: 1 | O10: IT_ONLY | P10: https://www.instagram.com/sifest/ | Q10: https://www.facebook.com/savignano.immagini | R10: 8 | S10: non-profit | T10: 1 | U10: 1 | V10: 0 | W10: 1 | X10: 1 | Y10: 1 | Z10: 1 | AA10: 0 | AB10: 0 | AC10: 1 | AD10: 1 | AE10: mixed | AF10: unknown | AG10: 0 | AI10: 46227
A11: FEST000012 | B11: ZeroNegativo | C11: Santeramo in Colle | D11: {=XLOOKUP(C11,Locations!A:A,Locations!D:D,"")} -> 3167327 | E11: {=XLOOKUP(C11,Locations!A:A,Locations!E:E,"")} -> Puglia | F11: {=XLOOKUP(C11,Locations!A:A,Locations!F:F,"")} -> ITF4 | G11: IT | H11: 2024 | I11: active | J11: 4 | K11: annual | L11: https://zeronegativofest.it/ | M11: null | N11: 1 | O11: IT_ONLY | P11: https://www.instagram.com/zeronegativofest/ | Q11: https://www.facebook.com/p/Zeronegativo-61573755717554/ | R11: 8 | S11: non-profit | T11: 1 | U11: 0 | V11: 0 | W11: 1 | X11: 1 | Y11: 1 | Z11: 1 | AA11: 0 | AB11: 1 | AC11: 0 | AD11: 1 | AE11: mixed | AF11: unknown | AG11: 1 | AH11: Festival itinerante tra Puglia e Toscana | AI11: 46227
A12: FEST000013 | B12: Festival Ubiqua | C12: Cinisello Balsamo | D12: {=XLOOKUP(C12,Locations!A:A,Locations!D:D,"")} -> 3178671 | E12: {=XLOOKUP(C12,Locations!A:A,Locations!E:E,"")} -> Lombardia | F12: {=XLOOKUP(C12,Locations!A:A,Locations!F:F,"")} -> ITC4 | G12: IT | H12: 2022 | I12: active | J12: 4 | K12: annual | L12: null | M12: https://munaf.it/ubiqua/ | N12: 0 | O12: IT_ONLY | P12: null | Q12: null | R12: 0 | S12: public | T12: 0 | U12: 0 | V12: 0 | W12: 0 | X12: 1 | Y12: 1 | Z12: 1 | AA12: 1 | AB12: 0 | AC12: 1 | AD12: 1 | AE12: historic_site | AF12: free | AG12: 0 | AI12: 46227
A13: FEST000014 | B13: Treviso Photographic Festival | C13: Treviso | D13: {=XLOOKUP(C13,Locations!A:A,Locations!D:D,"")} -> 3165201 | E13: {=XLOOKUP(C13,Locations!A:A,Locations!E:E,"")} -> Veneto | F13: {=XLOOKUP(C13,Locations!A:A,Locations!F:F,"")} -> ITH3 | G13: IT | H13: 2018 | I13: active | J13: 22 | K13: annual | L13: https://www.trevisophotographicfestival.it/ | M13: null | N13: 1 | O13: IT_EN | P13: https://www.instagram.com/trevisophotographicfestival/ | Q13: https://www.facebook.com/lab77associazione/ | R13: 9 | S13: non-profit | T13: 0 | U13: 0 | V13: 1 | W13: 1 | X13: 1 | Y13: 0 | Z13: 0 | AA13: 1 | AB13: 0 | AC13: 1 | AD13: 0 | AE13: public_space | AF13: unknown | AG13: 0 | AI13: 46227
A14: FEST000015 | B14: Ragusa Foto Festival | C14: Ragusa | D14: {=XLOOKUP(C14,Locations!A:A,Locations!D:D,"")} -> 2523650 | E14: {=XLOOKUP(C14,Locations!A:A,Locations!E:E,"")} -> Sicilia | F14: {=XLOOKUP(C14,Locations!A:A,Locations!F:F,"")} -> ITG1 | G14: IT | H14: 2012 | I14: active | J14: 32 | K14: annual | L14: https://www.ragusafotofestival.com/ | M14: null | N14: 1 | O14: IT_ONLY | P14: https://www.instagram.com/ragusa_fotofestival | Q14: https://www.facebook.com/ragusafotofestival | R14: 8 | S14: non-profit | T14: 1 | U14: 1 | V14: 1 | W14: 1 | X14: 1 | Y14: 1 | Z14: 1 | AA14: 1 | AB14: 0 | AC14: 0 | AD14: 0 | AE14: mixed | AF14: paid | AG14: 0 | AI14: 46227
A15: FEST000017 | B15: PhEst – Festival Internazionale di Fotografia e Arte | C15: Monopoli | D15: {=XLOOKUP(C15,Locations!A:A,Locations!D:D,"")} -> 3173131 | E15: {=XLOOKUP(C15,Locations!A:A,Locations!E:E,"")} -> Puglia | F15: {=XLOOKUP(C15,Locations!A:A,Locations!F:F,"")} -> ITF4 | G15: IT | H15: 2016 | I15: active | J15: 101 | K15: annual | L15: https://www.phest.info/ | M15: null | N15: 1 | O15: IT_EN | P15: https://www.instagram.com/_phest_ | Q15: https://www.facebook.com/PhESTSeeBeyondTheSea/ | R15: 9 | S15: non-profit | T15: 1 | W15: 1 | X15: 1 | Y15: 1 | Z15: 1 | AA15: 1 | AB15: 1 | AC15: 1 | AD15: 1 | AE15: mixed | AF15: paid | AG15: 0 | AI15: 46227
A16: FEST000018 | B16: Fotografia Calabria Festival | C16: San Lucido | D16: {=XLOOKUP(C16,Locations!A:A,Locations!D:D,"")} -> 2523435 | E16: {=XLOOKUP(C16,Locations!A:A,Locations!E:E,"")} -> Calabria | F16: {=XLOOKUP(C16,Locations!A:A,Locations!F:F,"")} -> ITF6 | G16: IT | H16: 2022 | I16: active | J16: 12 | K16: annual | L16: https://www.fotografiacalabriafestival.it/ | M16: null | N16: 1 | O16: IT_EN | P16: https://www.instagram.com/fotografiacalabriafestival?igsh=ZXh4NDd6aGdmNHZq | Q16: https://www.facebook.com/fotografiacalabriafestival | R16: 9 | S16: non-profit | T16: 1 | U16: 1 | V16: 0 | W16: 1 | X16: 1 | Y16: 0 | Z16: 1 | AA16: 1 | AB16: 1 | AC16: 0 | AD16: 0 | AE16: public_space | AF16: mixed | AG16: 0 | AI16: 46227
A17: FEST000021 | B17: Cortona On The Move | C17: Cortona | D17: {=XLOOKUP(C17,Locations!A:A,Locations!D:D,"")} -> 3177948 | E17: {=XLOOKUP(C17,Locations!A:A,Locations!E:E,"")} -> Toscana | F17: {=XLOOKUP(C17,Locations!A:A,Locations!F:F,"")} -> ITI1 | G17: IT | H17: 2011 | I17: active | J17: 108 | K17: annual | L17: https://www.cortonaonthemove.com/ | M17: null | N17: 1 | O17: IT_EN | P17: https://www.instagram.com/cortonaonthemove/ | Q17: https://www.facebook.com/festivalcortonaonthemove | R17: 9 | S17: non-profit | T17: 1 | U17: 1 | V17: 1 | X17: 1 | Y17: 0 | Z17: 1 | AB17: 0 | AC17: 0 | AD17: 1 | AE17: mixed | AF17: paid | AG17: 0
A18: FEST000024 | B18: Langhe Photo Festival | C18: Neive | D18: {=XLOOKUP(C18,Locations!A:A,Locations!D:D,"")} -> 6536417 | E18: {=XLOOKUP(C18,Locations!A:A,Locations!E:E,"")} -> Piemonte | F18: {=XLOOKUP(C18,Locations!A:A,Locations!F:F,"")} -> ITC1 | G18: IT | H18: 2023 | I18: inactive | J18: 119 | K18: annual | L18: https://langhephotofestival.com/ | M18: null | N18: 0 | O18: IT_ONLY | P18: https://www.instagram.com/langhephotofestival/ | Q18: https://www.facebook.com/LanghePhotoFestival/ | R18: 6 | S18: non-profit | T18: 1 | U18: 0 | V18: 0 | X18: 1 | Y18: 0 | Z18: 1 | AB18: 0 | AC18: 0 | AD18: 0 | AE18: mixed | AF18: paid | AG18: 0
A19: FEST000025 | B19: Festival del Reportage | C19: Ascoli Piceno | D19: {=XLOOKUP(C19,Locations!A:A,Locations!D:D,"")} -> 3182749 | E19: {=XLOOKUP(C19,Locations!A:A,Locations!E:E,"")} -> Marche | F19: {=XLOOKUP(C19,Locations!A:A,Locations!F:F,"")} -> ITI3 | G19: IT | H19: 2021 | I19: active | J19: 3 | K19: annual | L19: https://www.festivaldelreportage.it/ | M19: null | N19: 1 | O19: IT_ONLY | P19: https://www.instagram.com/festivaldelreportage/ | Q19: https://www.facebook.com/festivaldelreportage | R19: 8 | S19: non-profit | T19: 0 | U19: 0 | V19: 0 | X19: 1 | Y19: 0 | Z19: 1 | AB19: 0 | AC19: 0 | AD19: 1 | AE19: mixed | AF19: paid | AG19: 0
A20: FEST000026 | B20: Flaiano fO - Festival Internazionale di Fotografia e Giornalismo | C20: Pescara | D20: {=XLOOKUP(C20,Locations!A:A,Locations!D:D,"")} -> 3171168 | E20: {=XLOOKUP(C20,Locations!A:A,Locations!E:E,"")} -> Abruzzo | F20: {=XLOOKUP(C20,Locations!A:A,Locations!F:F,"")} -> ITF1 | G20: IT | H20: 2023 | I20: inactive | J20: 2 | K20: annual | L20: null | M20: https://www.premiflaiano.com/ | N20: 0 | O20: IT_EN | P20: null | Q20: null | R20: 1 | S20: non-profit | T20: 0 | U20: 0 | V20: 0 | W20: 1 | X20: 1 | Y20: 0 | Z20: 1 | AA20: 0 | AB20: 1 | AC20: 0 | AD20: 1 | AE20: cultural_space | AF20: free | AG20: 0
A21: FEST000027 | B21: GU.PHO. Photo Festival Internazionale Vernacolare | C21: Guiglia | D21: {=XLOOKUP(C21,Locations!A:A,Locations!D:D,"")} -> 3175676 | E21: {=XLOOKUP(C21,Locations!A:A,Locations!E:E,"")} -> Emilia-Romagna | F21: {=XLOOKUP(C21,Locations!A:A,Locations!F:F,"")} -> ITH5 | G21: IT | H21: 2022 | I21: active | J21: 9 | K21: annual | L21: https://gupho.art/ | M21: null | N21: 1 | O21: IT_EN | P21: https://www.instagram.com/gu.pho.festival/ | Q21: https://www.facebook.com/Gu.Pho.Festival/?locale=it_IT | R21: 9 | S21: non-profit | T21: 1 | U21: 0 | V21: 0 | X21: 1 | Y21: 0 | Z21: 1 | AB21: 0 | AC21: 0 | AD21: 1 | AE21: historic_site | AF21: free | AG21: 0
A22: FEST000028 | B22: Festival della Fotografia Italiana | C22: Bibbiena | D22: {=XLOOKUP(C22,Locations!A:A,Locations!D:D,"")} -> 3182059 | E22: {=XLOOKUP(C22,Locations!A:A,Locations!E:E,"")} -> Toscana | F22: {=XLOOKUP(C22,Locations!A:A,Locations!F:F,"")} -> ITI1 | G22: IT | H22: 2024 | I22: active | J22: 87 | K22: annual | L22: https://www.festivalfotografiaitaliana.it/ | M22: null | N22: 1 | O22: IT_ONLY | P22: https://www.instagram.com/insta.fiaf/ | Q22: https://www.facebook.com/fiaf.net | R22: 8 | S22: non-profit | T22: 1 | U22: 0 | V22: 0 | X22: 1 | Y22: 0 | Z22: 1 | AB22: 0 | AC22: 0 | AD22: 0 | AE22: mixed | AF22: mixed | AG22: 0
A23: FEST000029 | B23: Le Giornate della Luce | C23: Spilimbergo | D23: {=XLOOKUP(C23,Locations!A:A,Locations!D:D,"")} -> 3166262 | E23: {=XLOOKUP(C23,Locations!A:A,Locations!E:E,"")} -> Friuli-Venezia Giulia | F23: {=XLOOKUP(C23,Locations!A:A,Locations!F:F,"")} -> ITH4 | G23: IT | H23: 2015 | I23: active | J23: 9 | K23: annual | L23: http://www.legiornatedellaluce.it/ | M23: null | N23: 1 | O23: IT_ONLY | P23: https://www.instagram.com/legiornatedellaluce/ | Q23: https://www.facebook.com/legiornatedellaluce/?locale=it_IT | R23: 8 | S23: non-profit | T23: 1 | U23: 0 | V23: 1 | X23: 1 | Y23: 0 | Z23: 1 | AB23: 0 | AC23: 0 | AD23: 1 | AE23: mixed | AF23: mixed | AG23: 1
A24: FEST000030 | B24: Asincronie - Festival di Cinema documentario e Fotografia | C24: Sassari | D24: {=XLOOKUP(C24,Locations!A:A,Locations!D:D,"")} -> 3167096 | E24: {=XLOOKUP(C24,Locations!A:A,Locations!E:E,"")} -> Sardegna | F24: {=XLOOKUP(C24,Locations!A:A,Locations!F:F,"")} -> ITG2 | G24: IT | H24: 2020 | I24: active | J24: 32 | K24: annual | L24: https://www.asincronie.net/ | M24: null | N24: 1 | O24: IT_EN | P24: https://www.instagram.com/asincronie_festival/ | Q24: https://www.facebook.com/Asincronie-Festival-di-Cinema-Documentario-e-Fotografia-715947922539789 | R24: 9 | S24: non-profit | T24: 1 | U24: 1 | V24: 1 | X24: 1 | Y24: 0 | Z24: 1 | AB24: 0 | AC24: 1 | AD24: 1 | AE24: mixed | AF24: free | AG24: 0
A25: FEST000031 | B25: Fotografia Europea | C25: Reggio nell'Emilia | D25: {=XLOOKUP(C25,Locations!A:A,Locations!D:D,"")} -> 3169522 | E25: {=XLOOKUP(C25,Locations!A:A,Locations!E:E,"")} -> Emilia-Romagna | F25: {=XLOOKUP(C25,Locations!A:A,Locations!F:F,"")} -> ITH5 | G25: IT | H25: 2006 | I25: active | J25: 46 | K25: annual | L25: https://www.fotografiaeuropea.it/ | M25: null | N25: 1 | O25: IT_EN | P25: https://instagram.com/fotografia_europea/ | Q25: http://www.facebook.com/FotografiaEuropea | R25: 9 | S25: mixed | T25: 1 | U25: 1 | V25: 1 | X25: 1 | Y25: 0 | Z25: 1 | AB25: 0 | AC25: 1 | AD25: 1 | AE25: mixed | AF25: mixed | AG25: 1
A26: FEST000032 | B26: MIA Photo Fair BNP Paribas | C26: Milano | D26: {=XLOOKUP(C26,Locations!A:A,Locations!D:D,"")} -> 6951411 | E26: {=XLOOKUP(C26,Locations!A:A,Locations!E:E,"")} -> Lombardia | F26: {=XLOOKUP(C26,Locations!A:A,Locations!F:F,"")} -> ITC4 | G26: IT | H26: 2011 | I26: active | J26: 4 | K26: annual | L26: https://www.miafairbnpparibas.it/ | M26: null | N26: 1 | O26: IT_EN | P26: https://www.instagram.com/miaphotofair/ | Q26: https://www.facebook.com/miaphotofair/ | R26: 9 | S26: private | T26: 0 | U26: 1 | V26: 1 | X26: 1 | Y26: 1 | Z26: 1 | AB26: 1 | AC26: 0 | AD26: 1 | AE26: cultural_space | AF26: paid | AG26: 0
A27: FEST000033 | B27: Festival Fotografico Europeo | C27: Castellanza | D27: {=XLOOKUP(C27,Locations!A:A,Locations!D:D,"")} -> 3179650 | E27: {=XLOOKUP(C27,Locations!A:A,Locations!E:E,"")} -> Lombardia | F27: {=XLOOKUP(C27,Locations!A:A,Locations!F:F,"")} -> ITC4 | G27: IT | H27: 2013 | I27: active | J27: 50 | K27: annual | L27: https://www.europhotofestival.com/ | M27: null | N27: 1 | O27: IT_ONLY | P27: https://www.instagram.com/archiviofotograficoitaliano/ | Q27: https://www.facebook.com/archiviofotograficoitaliano/ | R27: 8 | S27: non-profit | T27: 1 | U27: 0 | V27: 1 | X27: 1 | Y27: 0 | Z27: 1 | AB27: 0 | AC27: 1 | AD27: 1 | AE27: mixed | AF27: free | AG27: 0 | AH27: Festival diffuso che coinvolge anche Legnano, Castellanza, Olgiate Olona, Cairate e altre sedi del territorio.
A28: FEST000034 | B28: Brescia Photo Festival | C28: Brescia | D28: {=XLOOKUP(C28,Locations!A:A,Locations!D:D,"")} -> 3181554 | E28: {=XLOOKUP(C28,Locations!A:A,Locations!E:E,"")} -> Lombardia | F28: {=XLOOKUP(C28,Locations!A:A,Locations!F:F,"")} -> ITC4 | G28: IT | H28: 2017 | I28: active | J28: 4 | K28: annual | L28: null | M28: https://www.bresciamusei.com/evento/brescia-photo-festival/ | N28: 0 | O28: IT_EN | P28: null | Q28: null | R28: 1 | S28: mixed | T28: 1 | U28: 0 | V28: 1 | X28: 1 | Y28: 0 | Z28: 1 | AB28: 0 | AC28: 0 | AD28: 1 | AE28: mixed | AF28: mixed | AG28: 0 | AH28: Il festival disponeva in passato di una presenza web autonoma; attualmente la comunicazione è integrata nei canali istituzionali di Fondazione Brescia Musei e Comune di Brescia. Non risultano profili social dedicati al festival, ma solo canali degli enti promotori.
A29: FEST000035 | B29: Photolux Festival | C29: Lucca | D29: {=XLOOKUP(C29,Locations!A:A,Locations!D:D,"")} -> 3174530 | E29: {=XLOOKUP(C29,Locations!A:A,Locations!E:E,"")} -> Toscana | F29: {=XLOOKUP(C29,Locations!A:A,Locations!F:F,"")} -> ITI1 | G29: IT | H29: 2005 | I29: active | J29: 51 | K29: biennial | L29: https://www.photoluxfestival.it/ | M29: null | N29: 0 | O29: IT_EN | P29: https://www.instagram.com/photoluxfest/ | Q29: https://www.facebook.com/PhotoluxFestival | R29: 7 | S29: non-profit | T29: 1 | U29: 0 | V29: 1 | X29: 1 | Y29: 0 | Z29: 1 | AB29: 0 | AC29: 0 | AD29: 0 | AE29: mixed | AF29: paid | AG29: 0 | AH29: Continuità storica con Lucca Photo Fest (2005); il brand Photolux Festival nasce nel 2012.
A30: FEST000036 | B30: Ricarica Foto Festival | C30: Sustinente | D30: {=XLOOKUP(C30,Locations!A:A,Locations!D:D,"")} -> 3166011 | E30: {=XLOOKUP(C30,Locations!A:A,Locations!E:E,"")} -> Lombardia | F30: {=XLOOKUP(C30,Locations!A:A,Locations!F:F,"")} -> ITC4 | G30: IT | H30: 2022 | I30: defunct | J30: 17 | K30: biennial | L30: https://ricaricafotofestival.it/home-page/ | M30: null | N30: 0 | O30: IT_ONLY | P30: null | Q30: null | R30: 2 | S30: non-profit | U30: 0 | V30: 0 | X30: 1 | Y30: 1 | Z30: 1 | AB30: 0 | AC30: 0 | AD30: 1 | AE30: mixed | AF30: paid | AG30: 1 | AH30: Ricarica Foto Festival concluso come format autonomo dopo l'edizione 2024; evoluto nel progetto BASC – Biennale d’Arte Sociale e di Comunità.
A31: FEST000037 | B31: Biennale della Fotografia Femminile | C31: Mantova | D31: {=XLOOKUP(C31,Locations!A:A,Locations!D:D,"")} -> 3174051 | E31: {=XLOOKUP(C31,Locations!A:A,Locations!E:E,"")} -> Lombardia | F31: {=XLOOKUP(C31,Locations!A:A,Locations!F:F,"")} -> ITC4 | G31: IT | H31: 2020 | I31: active | J31: 24 | K31: biennial | L31: https://www.bffmantova.com/ | M31: null | N31: 1 | O31: IT_EN | P31: https://www.instagram.com/bffmantova/ | Q31: https://www.facebook.com/bffmantova | R31: 9 | S31: non-profit | T31: 1 | U31: 1 | V31: 1 | X31: 1 | Y31: 0 | Z31: 1 | AB31: 0 | AC31: 0 | AD31: 1 | AE31: cultural_space | AF31: mixed | AG31: 0
A32: FEST000038 | B32: Milano Photofestival | C32: Milano | D32: {=XLOOKUP(C32,Locations!A:A,Locations!D:D,"")} -> 6951411 | E32: {=XLOOKUP(C32,Locations!A:A,Locations!E:E,"")} -> Lombardia | F32: {=XLOOKUP(C32,Locations!A:A,Locations!F:F,"")} -> ITC4 | G32: IT | H32: 2005 | I32: inactive | J32: 47 | K32: annual | L32: http://www.milanophotofestival.it/ | M32: null | N32: 0 | O32: IT_EN | P32: https://www.instagram.com/milanophotofestival/ | Q32: https://www.facebook.com/photofestivalmilano/ | R32: 7 | S32: non-profit | T32: 1 | U32: 0 | V32: 0 | X32: 1 | Y32: 0 | Z32: 1 | AB32: 0 | AC32: 0 | AD32: 1 | AE32: mixed | AF32: free | AG32: 1
A33: FEST000039 | B33: Umbria World Fest | C33: Foligno | D33: {=XLOOKUP(C33,Locations!A:A,Locations!D:D,"")} -> 3176854 | E33: {=XLOOKUP(C33,Locations!A:A,Locations!E:E,"")} -> Umbria | F33: {=XLOOKUP(C33,Locations!A:A,Locations!F:F,"")} -> ITI2 | G33: IT | H33: unknown | I33: inactive | J33: 3 | K33: annual | L33: http://www.umbriaworldfest.it/ | M33: null | N33: 0 | O33: IT_EN | P33: https://www.instagram.com/umbriaworldfest/ | Q33: https://www.facebook.com/UmbriaWorldFest/ | R33: 7 | S33: non-profit | T33: 1 | U33: 0 | V33: 0 | X33: 1 | Y33: 0 | Z33: 1 | AB33: 0 | AC33: 1 | AD33: 1 | AE33: mixed | AF33: mixed | AG33: 0
A34: FEST000040 | B34: ImagOrbetello Photo Festival | C34: Orbetello | D34: {=XLOOKUP(C34,Locations!A:A,Locations!D:D,"")} -> 3171985 | E34: {=XLOOKUP(C34,Locations!A:A,Locations!E:E,"")} -> Toscana | F34: {=XLOOKUP(C34,Locations!A:A,Locations!F:F,"")} -> ITI1 | G34: IT | H34: 2013 | I34: inactive | J34: unknown | K34: annual | L34: https://www.imagorbetello.com/ | M34: null | N34: 0 | O34: IT_ONLY | P34: https://www.instagram.com/imago.photofestival/ | Q34: https://www.facebook.com/ImagOrbetello | R34: 6 | S34: non-profit | T34: 1 | U34: 1 | V34: 1 | X34: 1 | Y34: 0 | Z34: 1 | AB34: 0 | AC34: 0 | AD34: 1 | AE34: mixed | AF34: free | AG34: 0
A35: FEST000041 | B35: CHARTA: a Photobook Festival | C35: Roma | D35: {=XLOOKUP(C35,Locations!A:A,Locations!D:D,"")} -> 8957247 | E35: {=XLOOKUP(C35,Locations!A:A,Locations!E:E,"")} -> Lazio | F35: {=XLOOKUP(C35,Locations!A:A,Locations!F:F,"")} -> ITI4 | G35: IT | H35: 2021 | I35: active | J35: 9 | K35: biennial | L35: https://chartafestival.com/it/ | M35: null | N35: 1 | O35: IT_EN | P35: https://www.instagram.com/chartafestival/?hl=it | Q35: https://www.facebook.com/ChartaFestival/ | R35: 9 | S35: non-profit | T35: 1 | U35: 1 | V35: 1 | X35: 1 | Y35: 0 | Z35: 1 | AB35: 0 | AC35: 0 | AD35: 0 | AE35: cultural_space | AF35: free | AG35: 0
A36: FEST000042 | B36: Molichrom: Festical della Fotografia Nomade | C36: Campobasso | D36: {=XLOOKUP(C36,Locations!A:A,Locations!D:D,"")} -> 3180991 | E36: {=XLOOKUP(C36,Locations!A:A,Locations!E:E,"")} -> Molise | F36: {=XLOOKUP(C36,Locations!A:A,Locations!F:F,"")} -> ITF2 | G36: IT | H36: 2022 | I36: active | J36: 47 | K36: annual | L36: https://www.molichrom.com/ | M36: null | N36: 1 | O36: IT_ONLY | P36: https://www.instagram.com/molichrom_festival | Q36: https://www.facebook.com/molichrom | R36: 8 | S36: non-profit | T36: 1 | U36: 0 | V36: 0 | X36: 1 | Y36: 0 | Z36: 1 | AB36: 0 | AC36: 0 | AD36: 1 | AE36: mixed | AF36: mixed | AG36: 0
A37: FEST000043 | B37: PhotoVogue Festival | C37: Milano | D37: {=XLOOKUP(C37,Locations!A:A,Locations!D:D,"")} -> 6951411 | E37: {=XLOOKUP(C37,Locations!A:A,Locations!E:E,"")} -> Lombardia | F37: {=XLOOKUP(C37,Locations!A:A,Locations!F:F,"")} -> ITC4 | G37: IT | H37: 2016 | I37: active | J37: 4 | K37: annual | L37: null | M37: https://www.vogue.it/article/photovogue-festival-2026-programma-cosa-sapere-location | N37: 0 | O37: IT_ONLY | P37: https://www.instagram.com/photovogue/ | Q37: null | R37: 2 | S37: private | T37: 0 | U37: 1 | V37: 1 | X37: 1 | Y37: 1 | Z37: 0 | AB37: 0 | AC37: 0 | AD37: 1 | AE37: cultural_space | AF37: free | AG37: 0
A38: FEST000044 | B38: Liquida Photofestival | C38: Torino | D38: {=XLOOKUP(C38,Locations!A:A,Locations!D:D,"")} -> 8980539 | E38: {=XLOOKUP(C38,Locations!A:A,Locations!E:E,"")} -> Piemonte | F38: {=XLOOKUP(C38,Locations!A:A,Locations!F:F,"")} -> ITC1 | G38: IT | H38: 2022 | I38: active | J38: 3 | K38: annual | L38: null | M38: https://www.paratissima.it/liquida-photofestival-2026/ | N38: 0 | O38: IT_ONLY | P38: https://www.instagram.com/liquidaphotofestival/ | Q38: null | R38: 2 | S38: non-profit | T38: 0 | U38: 1 | V38: 0 | X38: 1 | Y38: 1 | Z38: 1 | AB38: 0 | AC38: 0 | AD38: 0 | AE38: historic_site | AF38: paid | AG38: 0
A39: FEST000045 | B39: Corigliano Calabro Fotografia | C39: Corigliano-Rossano | D39: {=XLOOKUP(C39,Locations!A:A,Locations!D:D,"")} -> 12032199 | E39: {=XLOOKUP(C39,Locations!A:A,Locations!E:E,"")} -> Calabria | F39: {=XLOOKUP(C39,Locations!A:A,Locations!F:F,"")} -> ITF6 | G39: IT | H39: 2003 | I39: active | J39: 58 | K39: annual | L39: https://www.coriglianocalabrofotografia.it/ | N39: 1 | O39: IT_ONLY | P39: https://www.instagram.com/coriglianocalabrofotografia/ | Q39: https://www.facebook.com/coriglianocalabrofotografia/?locale=it_IT | R39: 8 | S39: non-profit | T39: 1 | U39: 0 | V39: 0 | X39: 1 | Y39: 0 | Z39: 1 | AB39: 0 | AC39: 0 | AD39: 0 | AE39: historic_site | AF39: free | AG39: 0
A40: FEST000046 | B40: Festival di Fotografia Montefano Arturo Ghergo | C40: Montefano | D40: {=XLOOKUP(C40,Locations!A:A,Locations!D:D,"")} -> 3172935 | E40: {=XLOOKUP(C40,Locations!A:A,Locations!E:E,"")} -> Marche | F40: {=XLOOKUP(C40,Locations!A:A,Locations!F:F,"")} -> ITI3 | G40: IT | H40: 2015 | I40: active | J40: 3 | K40: annual | L40: https://www.festivalarturoghergo.com/ | N40: 1 | O40: IT_ONLY | P40: https://www.instagram.com/festival_fotografia_montefano | Q40: https://it-it.facebook.com/effettoghergo/ | R40: 8 | S40: non-profit | T40: 1 | U40: 0 | V40: 0 | X40: 1 | Y40: 0 | Z40: 1 | AB40: 0 | AC40: 0 | AD40: 1 | AE40: historic_site | AF40: mixed | AG40: 0
A41: FEST000047 | B41: Funzilla Fest | C41: Roma | D41: {=XLOOKUP(C41,Locations!A:A,Locations!D:D,"")} -> 8957247 | E41: {=XLOOKUP(C41,Locations!A:A,Locations!E:E,"")} -> Lazio | F41: {=XLOOKUP(C41,Locations!A:A,Locations!F:F,"")} -> ITI4 | G41: IT | H41: 2016 | I41: active | J41: 3 | K41: annual | L41: https://www.funzillafest.com/ | M41: null | N41: 1 | O41: IT_ONLY | P41: https://www.instagram.com/funzilla_fest/?hl=it | Q41: https://www.facebook.com/funzillafest/?locale=it_IT | R41: 8 | S41: non-profit | T41: 0 | U41: 1 | V41: 0 | X41: 1 | Y41: 0 | Z41: 1 | AB41: 0 | AC41: 0 | AD41: 0 | AE41: cultural_space | AF41: free | AG41: 0
A42: FEST000048 | B42: Castelnuovo Fotografia | C42: Castelnuovo di Porto | D42: {=XLOOKUP(C42,Locations!A:A,Locations!D:D,"")} -> 3179521 | E42: {=XLOOKUP(C42,Locations!A:A,Locations!E:E,"")} -> Lazio | F42: {=XLOOKUP(C42,Locations!A:A,Locations!F:F,"")} -> ITI4 | G42: IT | H42: 2013 | I42: inactive | J42: 9 | K42: annual | L42: https://www.castelnuovofotografia.it/ | M42: null | N42: 0 | O42: IT_ONLY | P42: https://www.instagram.com/castelnuovo_fotografia/ | Q42: https://www.facebook.com/cdp.fotografia/ | R42: 6 | S42: non-profit | T42: 1 | U42: 0 | V42: 1 | X42: 1 | Y42: 1 | Z42: 1 | AA42: 1 | AB42: 1 | AC42: 1 | AD42: 1 | AE42: historic_site | AF42: free | AG42: 0
A43: FEST000049 | B43: Cosmo Photo Fest | C43: Colleferro | D43: {=XLOOKUP(C43,Locations!A:A,Locations!D:D,"")} -> 3178398 | E43: {=XLOOKUP(C43,Locations!A:A,Locations!E:E,"")} -> Lazio | F43: {=XLOOKUP(C43,Locations!A:A,Locations!F:F,"")} -> ITI4 | G43: IT | H43: 2024 | I43: inactive | J43: 31 | K43: unknown | L43: https://www.cosmophotofest.it/ | M43: null | N43: 0 | O43: IT_EN | P43: https://www.instagram.com/cosmophoto.fest?igsh=ZGx1N3Y2YXVkdTds | Q43: https://www.facebook.com/Cosmophoto.fest | R43: 7 | S43: non-profit | T43: 0 | U43: 1 | V43: 0 | X43: 1 | Y43: 1 | Z43: 1 | AB43: 0 | AC43: 1 | AD43: 1 | AE43: mixed | AF43: free | AG43: 0
A44: FEST000050 | B44: Exposed Torino Foto Festival | C44: Torino | D44: {=XLOOKUP(C44,Locations!A:A,Locations!D:D,"")} -> 8980539 | E44: {=XLOOKUP(C44,Locations!A:A,Locations!E:E,"")} -> Piemonte | F44: {=XLOOKUP(C44,Locations!A:A,Locations!F:F,"")} -> ITC1 | G44: IT | H44: 2024 | I44: active | J44: 48 | K44: annual | L44: https://exposed.to.it/ | M44: null | N44: 1 | O44: IT_EN | P44: https://www.instagram.com/torino.foto.festival/ | Q44: https://www.facebook.com/p/Exposed-Torino-Foto-Festival-61552664212438/ | R44: 9 | S44: mixed | T44: 1 | U44: 1 | V44: 1 | X44: 1 | Y44: 1 | Z44: 1 | AB44: 0 | AC44: 0 | AD44: 1 | AE44: mixed | AF44: mixed | AG44: 0
A45: FEST000051 | B45: The Phair - Photo Art Fair | C45: Torino | D45: {=XLOOKUP(C45,Locations!A:A,Locations!D:D,"")} -> 8980539 | E45: {=XLOOKUP(C45,Locations!A:A,Locations!E:E,"")} -> Piemonte | F45: {=XLOOKUP(C45,Locations!A:A,Locations!F:F,"")} -> ITC1 | G45: IT | H45: 2019 | I45: active | J45: 3 | K45: annual | L45: www.thephair.com | M45: null | N45: 1 | O45: IT_EN | P45: https://www.instagram.com/thephair_photoartfair | Q45: https://www.facebook.com/thephairphotoartfair/ | R45: 9 | S45: private | T45: 0 | U45: 0 | V45: 0 | X45: 1 | Y45: 1 | Z45: 0 | AB45: 0 | AC45: 0 | AD45: 1 | AE45: cultural_space | AF45: paid | AG45: 0
A46: FEST000052 | B46: Trieste Photo Days | C46: Trieste | D46: {=XLOOKUP(C46,Locations!A:A,Locations!D:D,"")} -> 3165185 | E46: {=XLOOKUP(C46,Locations!A:A,Locations!E:E,"")} -> Friuli-Venezia Giulia | F46: {=XLOOKUP(C46,Locations!A:A,Locations!F:F,"")} -> ITH4 | G46: IT | H46: 2014 | I46: active | J46: 4 | K46: annual | L46: https://www.triestephotodays.com/ | M46: null | N46: 1 | O46: IT_EN | P46: https://www.instagram.com/triestephotodays | Q46: https://www.facebook.com/triestephotodays | R46: 9 | S46: non-profit | T46: 1 | U46: 1 | V46: 1 | X46: 1 | Y46: 0 | Z46: 1 | AB46: 1 | AC46: 0 | AD46: 1 | AE46: mixed | AF46: mixed | AG46: 0
A47: FEST000053 | B47: Oculus Foto Festival | C47: Venezia | D47: {=XLOOKUP(C47,Locations!A:A,Locations!D:D,"")} -> 3175005 | E47: {=XLOOKUP(C47,Locations!A:A,Locations!E:E,"")} -> Veneto | F47: {=XLOOKUP(C47,Locations!A:A,Locations!F:F,"")} -> ITH3 | G47: IT | H47: 2022 | I47: inactive | J47: 102 | K47: unknown | L47: https://oculusfotofestival.com/ | M47: null | N47: 0 | O47: IT_EN | P47: https://www.instagram.com/off.venezia/ | Q47: https://www.facebook.com/oculusfotofestival/ | R47: 7 | S47: non-profit | T47: 0 | U47: 0 | V47: 1 | X47: 1 | Y47: 1 | Z47: 0 | AB47: 0 | AC47: 0 | AD47: 0 | AE47: museum_gallery | AF47: unknown | AG47: 0
A48: FEST000054 | B48: Biennale di Fotografia di Portogruaro | C48: Portogruaro | D48: {=XLOOKUP(C48,Locations!A:A,Locations!D:D,"")} -> 3170086 | E48: {=XLOOKUP(C48,Locations!A:A,Locations!E:E,"")} -> Veneto | F48: {=XLOOKUP(C48,Locations!A:A,Locations!F:F,"")} -> ITH3 | G48: IT | H48: 2023 | I48: inactive | J48: unknown | K48: biennial | L48: https://www.biennalefotografiaportogruaro.com/ | M48: null | N48: 0 | O48: IT_EN | P48: https://www.instagram.com/biennalefotografiaportogruaro/ | Q48: https://www.facebook.com/galleriaimolini/?locale=it_IT | R48: 7 | S48: non-profit | T48: 0 | U48: 1 | V48: 0 | X48: 1 | Y48: 1 | Z48: 0 | AB48: 1 | AC48: 0 | AD48: 0 | AE48: museum_gallery | AF48: free | AG48: 0
A49: FEST000055 | B49: PhMuseum Days | C49: Bologna | D49: {=XLOOKUP(C49,Locations!A:A,Locations!D:D,"")} -> 3181928 | E49: {=XLOOKUP(C49,Locations!A:A,Locations!E:E,"")} -> Emilia-Romagna | F49: {=XLOOKUP(C49,Locations!A:A,Locations!F:F,"")} -> ITH5 | G49: IT | H49: 2021 | I49: active | J49: 4 | K49: annual | L49: https://phmuseumdays.it/ | M49: null | N49: 1 | O49: IT_EN | P49: https://www.instagram.com/phmuseumdays | Q49: https://www.facebook.com/phmuseumdays | R49: 9 | S49: non-profit | T49: 1 | U49: 1 | V49: 0 | X49: 1 | Y49: 0 | Z49: 1 | AB49: 0 | AC49: 0 | AD49: 1 | AE49: mixed | AF49: paid | AG49: 0
A50: FEST000056 | B50: Gibellina Photoroad Festival | C50: Gibellina | D50: {=XLOOKUP(C50,Locations!A:A,Locations!D:D,"")} -> 2524614 | E50: {=XLOOKUP(C50,Locations!A:A,Locations!E:E,"")} -> Sicilia | F50: {=XLOOKUP(C50,Locations!A:A,Locations!F:F,"")} -> ITG1 | G50: IT | H50: 2016 | I50: active | J50: 65 | K50: biennial | L50: https://gibellinaphotoroadfestival.com/it/ | M50: null | N50: 1 | O50: IT_EN | P50: https://www.instagram.com/gibellinaphotoroad/ | Q50: https://www.facebook.com/GibellinaPhotoRoad | R50: 9 | S50: non-profit | T50: 1 | U50: 1 | V50: 1 | X50: 1 | Y50: 1 | Z50: 1 | AB50: 1 | AC50: 0 | AD50: 1 | AE50: public_space | AF50: free | AG50: 0
A51: FEST000057 | B51: Fotografia Zeropixel | C51: Trieste | D51: {=XLOOKUP(C51,Locations!A:A,Locations!D:D,"")} -> 3165185 | E51: {=XLOOKUP(C51,Locations!A:A,Locations!E:E,"")} -> Friuli-Venezia Giulia | F51: {=XLOOKUP(C51,Locations!A:A,Locations!F:F,"")} -> ITH4 | G51: IT | H51: 2014 | I51: inactive | J51: 11 | K51: annual | L51: https://www.fotografiazeropixel.it/ | M51: null | N51: 0 | O51: IT_ONLY | P51: https://www.instagram.com/fotografiazeropixel/ | Q51: https://www.facebook.com/Fotografiazeropixel/ | R51: 6 | S51: non-profit | T51: 1 | U51: 1 | V51: 0 | X51: 1 | Y51: 0 | Z51: 0 | AB51: 0 | AC51: 0 | AD51: 1 | AE51: mixed | AF51: unknown | AG51: 0
A52: FEST000058 | B52: ColornoPhotoLife | C52: Colorno | D52: {=XLOOKUP(C52,Locations!A:A,Locations!D:D,"")} -> 3178263 | E52: {=XLOOKUP(C52,Locations!A:A,Locations!E:E,"")} -> Emilia-Romagna | F52: {=XLOOKUP(C52,Locations!A:A,Locations!F:F,"")} -> ITH5 | G52: IT | H52: 2009 | I52: active | J52: 45 | K52: annual | L52: www.colornophotolife.it | M52: null | N52: 1 | O52: IT_ONLY | P52: https://www.instagram.com/colornophotolife/ | Q52: https://www.facebook.com/groups/223731227644440/ | R52: 8 | S52: non-profit | T52: 1 | U52: 1 | V52: 0 | X52: 1 | Y52: 0 | Z52: 1 | AB52: 0 | AC52: 0 | AD52: 1 | AE52: mixed | AF52: mixed | AG52: 0
A53: FEST000059 | B53: ArtVerona | C53: Verona | D53: {=XLOOKUP(C53,Locations!A:A,Locations!D:D,"")} -> 3164527 | E53: {=XLOOKUP(C53,Locations!A:A,Locations!E:E,"")} -> Veneto | F53: {=XLOOKUP(C53,Locations!A:A,Locations!F:F,"")} -> ITH3 | G53: IT | H53: 2005 | I53: active | J53: 3 | K53: annual | L53: https://artverona.it/ | M53: null | N53: 1 | O53: IT_EN | P53: https://www.instagram.com/artverona/ | Q53: https://www.facebook.com/artveronafieradarte | R53: 9 | S53: private | T53: 0 | U53: 0 | V53: 1 | X53: 1 | Y53: 1 | Z53: 1 | AB53: 1 | AC53: 1 | AD53: 1 | AE53: cultural_space | AF53: paid | AG53: 1
A54: FEST000060 | B54: Festival Diecixdieci | C54: Mantova | D54: {=XLOOKUP(C54,Locations!A:A,Locations!D:D,"")} -> 3174051 | E54: {=XLOOKUP(C54,Locations!A:A,Locations!E:E,"")} -> Lombardia | F54: {=XLOOKUP(C54,Locations!A:A,Locations!F:F,"")} -> ITC4 | G54: IT | H54: 2015 | I54: active | J54: 9 | K54: annual | L54: https://www.festivaldiecixdieci.it/ | M54: null | N54: 1 | O54: IT_ONLY | P54: https://www.instagram.com/festival.diecixdieci/ | Q54: https://www.facebook.com/festivaldiecixdieci/ | R54: 8 | S54: non-profit | T54: 0 | U54: 1 | V54: 0 | X54: 1 | Y54: 0 | Z54: 1 | AB54: 0 | AC54: 0 | AD54: 1 | AE54: historic_site | AF54: free | AG54: 0
A55: FEST000061 | B55: TERRA! Festival di Fotografia e Cinema | C55: Roma | D55: {=XLOOKUP(C55,Locations!A:A,Locations!D:D,"")} -> 8957247 | E55: {=XLOOKUP(C55,Locations!A:A,Locations!E:E,"")} -> Lazio | F55: {=XLOOKUP(C55,Locations!A:A,Locations!F:F,"")} -> ITI4 | G55: IT | H55: 2022 | I55: inactive | J55: 8 | K55: annual | L55: https://terra.collettivowsp.org/ | M55: null | N55: 0 | O55: IT_ONLY | P55: null | Q55: null | R55: 2 | S55: non-profit | T55: 1 | U55: 0 | V55: 0 | X55: 1 | Y55: 0 | Z55: 1 | AB55: 0 | AC55: 1 | AD55: 1 | AE55: public_space | AF55: free | AG55: 1
A56: FEST000062 | B56: Voghera Fotografia - Festival Nazionale di Fotografia | C56: Voghera | D56: {=XLOOKUP(C56,Locations!A:A,Locations!D:D,"")} -> 3163995 | E56: {=XLOOKUP(C56,Locations!A:A,Locations!E:E,"")} -> Lombardia | F56: {=XLOOKUP(C56,Locations!A:A,Locations!F:F,"")} -> ITC4 | G56: IT | H56: 2018 | I56: active | J56: 16 | K56: annual | L56: https://www.vogherafotografia.it/ | M56: null | N56: 1 | O56: IT_ONLY | P56: http://www.instagram.com/vogherafotografia | Q56: http://www.facebook.com/Voghera-Fotografia-2204091109821407 | R56: 8 | S56: non-profit | T56: 1 | U56: 0 | V56: 0 | X56: 1 | Y56: 0 | Z56: 1 | AB56: 0 | AC56: 0 | AD56: 1 | AE56: historic_site | AF56: free | AG56: 0
A57: FEST000063 | B57: Pangea Photo Festival | C57: Castelnovo ne' Monti | D57: {=XLOOKUP(C57,Locations!A:A,Locations!D:D,"")} -> 3179546 | E57: {=XLOOKUP(C57,Locations!A:A,Locations!E:E,"")} -> Emilia-Romagna | F57: {=XLOOKUP(C57,Locations!A:A,Locations!F:F,"")} -> ITH5 | G57: IT | H57: 2021 | I57: inactive | J57: 93 | K57: annual | L57: https://www.pangeaphotofestival.it/ | M57: null | N57: 0 | O57: IT_ONLY | P57: https://www.instagram.com/pangeaphotofestival/ | Q57: https://www.facebook.com/pangeaphotofestival/ | R57: 6 | S57: non-profit | T57: 1 | U57: 0 | V57: 0 | W57: 0 | X57: 1 | Y57: 0 | Z57: 0 | AB57: 0 | AC57: 0 | AD57: 0 | AE57: mixed | AF57: free | AG57: 1
A58: FEST000064 | B58: Fotoleggendo | C58: Roma | D58: {=XLOOKUP(C58,Locations!A:A,Locations!D:D,"")} -> 8957247 | E58: {=XLOOKUP(C58,Locations!A:A,Locations!E:E,"")} -> Lazio | F58: {=XLOOKUP(C58,Locations!A:A,Locations!F:F,"")} -> ITI4 | G58: IT | H58: 2005 | I58: inactive | J58: 27 | K58: annual | L58: https://www.fotoleggendo.it/ | M58: null | N58: 0 | O58: IT_ONLY | P58: https://www.instagram.com/fotoleggendo/ | Q58: https://www.facebook.com/FotoLeggendo/?locale=it_IT | R58: 6 | S58: non-profit | T58: 1 | U58: 0 | V58: 1 | X58: 1 | Y58: 0 | Z58: 1 | AB58: 0 | AC58: 0 | AD58: 1 | AE58: mixed | AF58: free | AG58: 0
A59: FEST000065 | B59: Fiumefreddo Photo Festival | C59: Fiumefreddo Bruzio | D59: {=XLOOKUP(C59,Locations!A:A,Locations!D:D,"")} -> 2524743 | E59: {=XLOOKUP(C59,Locations!A:A,Locations!E:E,"")} -> Calabria | F59: {=XLOOKUP(C59,Locations!A:A,Locations!F:F,"")} -> ITF6 | G59: IT | H59: 2022 | I59: inactive | J59: 44 | K59: unknown | L59: null | M59: https://calabriastraordinaria.it/eventi/fiumefreddo-photo-festival | N59: 0 | O59: IT_ONLY | P59: null | Q59: null | R59: 0 | S59: non-profit | T59: 0 | U59: 0 | V59: 0 | X59: 1 | Y59: 0 | Z59: 0 | AB59: 0 | AC59: 0 | AD59: 0 | AE59: public_space | AF59: free | AG59: 0
A60: FEST000066 | B60: MonFest | C60: Casale Monferrato | D60: {=XLOOKUP(C60,Locations!A:A,Locations!D:D,"")} -> 3180208 | E60: {=XLOOKUP(C60,Locations!A:A,Locations!E:E,"")} -> Piemonte | F60: {=XLOOKUP(C60,Locations!A:A,Locations!F:F,"")} -> ITC1 | G60: IT | H60: 2022 | I60: active | J60: 156 | K60: biennial | L60: https://monfestcasale.it/ | M60: null | N60: 1 | O60: IT_ONLY | P60: https://www.instagram.com/monfest24_25 | Q60: https://www.facebook.com/profile.php?id=61567125914451 | R60: 8 | S60: public | T60: 1 | U60: 1 | V60: 0 | X60: 1 | Y60: 0 | Z60: 0 | AB60: 0 | AC60: 1 | AD60: 1 | AE60: mixed | AF60: paid | AG60: 0
A61: FEST000067 | B61: Raise Your Zine! | C61: Napoli | D61: {=XLOOKUP(C61,Locations!A:A,Locations!D:D,"")} -> 3172394 | E61: {=XLOOKUP(C61,Locations!A:A,Locations!E:E,"")} -> Campania | F61: {=XLOOKUP(C61,Locations!A:A,Locations!F:F,"")} -> ITF3 | G61: IT | H61: unknown | I61: active | J61: 3 | K61: annual | L61: null | M61: https://www.welcometothedocks.org/raise-your-zine/ | N61: 0 | O61: IT_EN | P61: null | Q61: null | R61: 1 | S61: non-profit | T61: 0 | U61: 1 | V61: 0 | X61: 1 | Y61: 0 | Z61: 1 | AB61: 0 | AC61: 0 | AD61: 0 | AE61: cultural_space | AF61: unknown | AG61: 0
A62: FEST000068 | B62: Riaperture PhotoFestival Ferrara | C62: Ferrara | D62: {=XLOOKUP(C62,Locations!A:A,Locations!D:D,"")} -> 3177090 | E62: {=XLOOKUP(C62,Locations!A:A,Locations!E:E,"")} -> Emilia-Romagna | F62: {=XLOOKUP(C62,Locations!A:A,Locations!F:F,"")} -> ITH5 | G62: IT | H62: 2017 | I62: inactive | J62: 17 | K62: annual | L62: null | M62: https://www.comune.ferrara.it/z/315/view?modelClass=elitedivision%5Camos%5Cevents%5Cmodels%5CEvent&view=detailEvento | N62: 0 | O62: IT_ONLY | P62: https://www.instagram.com/riaperturefe/?hl=it | Q62: https://www.facebook.com/riaperture/?locale=it_IT | R62: 4 | S62: non-profit | T62: 0 | U62: 0 | V62: 0 | X62: 1 | Y62: 0 | Z62: 1 | AB62: 0 | AC62: 1 | AD62: 0 | AE62: mixed | AF62: paid | AG62: 0
A63: FEST000069 | B63: Italian Street Photo Festival | C63: Roma | D63: {=XLOOKUP(C63,Locations!A:A,Locations!D:D,"")} -> 8957247 | E63: {=XLOOKUP(C63,Locations!A:A,Locations!E:E,"")} -> Lazio | F63: {=XLOOKUP(C63,Locations!A:A,Locations!F:F,"")} -> ITI4 | G63: IT | H63: 2018 | I63: inactive | J63: 3 | K63: annual | L63: null | M63: https://www.photographers.it/festival/italian-street-photo-festival-2024/ | N63: 0 | O63: IT_ONLY | P63: https://www.instagram.com/italianstreetphotofestival/ | Q63: https://www.facebook.com/ItalianStreetPhotoFestival/?locale=it_IT | R63: 4 | S63: non-profit | T63: 0 | U63: 1 | V63: 0 | W63: unknown | X63: 1 | Y63: 0 | Z63: 0 | AB63: 0 | AC63: 0 | AD63: 0 | AE63: cultural_space | AF63: free | AG63: 0
A64: FEST000070 | B64: Napoli PHOTO Festival | C64: Napoli | D64: {=XLOOKUP(C64,Locations!A:A,Locations!D:D,"")} -> 3172394 | E64: {=XLOOKUP(C64,Locations!A:A,Locations!E:E,"")} -> Campania | F64: {=XLOOKUP(C64,Locations!A:A,Locations!F:F,"")} -> ITF3 | G64: IT | H64: 2024 | I64: active | J64: 10 | K64: annual | L64: https://napoliphotofestival.it/ | M64: null | N64: 1 | O64: IT_ONLY | P64: https://www.instagram.com/roregeneration/ | Q64: https://www.facebook.com/roregeneration/ | R64: 8 | S64: non-profit | T64: 1 | U64: 0 | V64: 0 | W64: 0 | X64: 1 | Y64: 0 | Z64: 0 | AB64: 0 | AC64: 0 | AD64: 1 | AE64: public_space | AF64: free | AG64: 0
A65: FEST000071 | B65: Radar Photo Festival | C65: Trani | D65: {=XLOOKUP(C65,Locations!A:A,Locations!D:D,"")} -> 3165322 | E65: {=XLOOKUP(C65,Locations!A:A,Locations!E:E,"")} -> Puglia | F65: {=XLOOKUP(C65,Locations!A:A,Locations!F:F,"")} -> ITF4 | G65: IT | H65: 2018 | I65: inactive | J65: 58 | K65: mixed | L65: https://www.radarphotofestival.it/ | M65: null | N65: 0 | O65: IT_ONLY | P65: https://www.instagram.com/radarfestivalphotography?igsh=MW1uZWN4bDg1ZXA2ZA== | Q65: https://www.facebook.com/radarphotofestival/?locale=it_IT | R65: 6 | S65: non-profit | T65: 1 | U65: 1 | V65: 1 | W65: 1 | X65: 1 | Y65: 1 | Z65: 1 | AB65: 0 | AC65: 0 | AD65: 0 | AE65: mixed | AF65: free | AG65: 1
A66: FEST000072 | B66: Fotografica - Festival di Fotografia Bergamo | C66: Bergamo | D66: {=XLOOKUP(C66,Locations!A:A,Locations!D:D,"")} -> 3182164 | E66: {=XLOOKUP(C66,Locations!A:A,Locations!E:E,"")} -> Lombardia | F66: {=XLOOKUP(C66,Locations!A:A,Locations!F:F,"")} -> ITC4 | G66: IT | H66: 2016 | I66: active | J66: 30 | K66: biennial | L66: https://fotograficafestival.it/ | M66: null | N66: 1 | O66: IT_EN | P66: https://www.instagram.com/fotograficabergamofestival/ | Q66: https://www.facebook.com/fotograficabergamofestival/ | R66: 9 | S66: non-profit | T66: 1 | U66: 1 | V66: 1 | W66: 1 | X66: 1 | Y66: 0 | Z66: 1 | AB66: 0 | AC66: 0 | AD66: 0 | AE66: historic_site | AF66: paid | AG66: 0
A67: FEST000073 | B67: Immagini sul Lago Photofest | C67: Trevignano Romano | D67: {=XLOOKUP(C67,Locations!A:A,Locations!D:D,"")} -> 3165205 | E67: {=XLOOKUP(C67,Locations!A:A,Locations!E:E,"")} -> Lazio | F67: {=XLOOKUP(C67,Locations!A:A,Locations!F:F,"")} -> ITI4 | G67: IT | H67: 2023 | I67: active | J67: 9 | K67: annual | L67: https://immagini-sul-lago.it/ | M67: null | N67: 1 | O67: IT_ONLY | P67: https://www.instagram.com/immagini_sul_lago/ | Q67: https://www.facebook.com/immaginisullago/?locale=it_IT | R67: 8 | S67: non-profit | T67: 0 | U67: 0 | V67: 0 | W67: 0 | X67: 1 | Y67: 0 | Z67: 0 | AB67: 0 | AC67: 0 | AD67: 0 | AE67: mixed | AF67: free | AG67: 1 | AH67: festival diffuso all’aperto, che coinvolgerà i borghi di Trevignano Romano, Anguillara Sabazia, Bracciano e Vigna di Valle
A68: FEST000074 | B68: Closer - Dentro il reportage | C68: Bologna | D68: {=XLOOKUP(C68,Locations!A:A,Locations!D:D,"")} -> 3181928 | E68: {=XLOOKUP(C68,Locations!A:A,Locations!E:E,"")} -> Emilia-Romagna | F68: {=XLOOKUP(C68,Locations!A:A,Locations!F:F,"")} -> ITH5 | G68: IT | H68: 2017 | I68: active | J68: 23 | K68: biennial | L68: null | M68: https://qrphotogallery.it/qrphotogallery | N68: 0 | O68: IT_ONLY | P68: https://www.instagram.com/closer.reportage/ | Q68: https://www.facebook.com/p/Closer-Dentro-il-reportage-61564497286489/ | R68: 4 | S68: non-profit | T68: 1 | U68: 1 | V68: 0 | W68: 1 | X68: 1 | Y68: 0 | Z68: 1 | AB68: 0 | AC68: 0 | AD68: 0 | AE68: historic_site | AF68: mixed | AG68: 0 | AH68: Si svolge tra Bologna e Budrio
A69: FEST000075 | B69: Pisa Street Photography International Festival | C69: Pisa | D69: {=XLOOKUP(C69,Locations!A:A,Locations!D:D,"")} -> 3170647 | E69: {=XLOOKUP(C69,Locations!A:A,Locations!E:E,"")} -> Toscana | F69: {=XLOOKUP(C69,Locations!A:A,Locations!F:F,"")} -> ITI1 | G69: IT | H69: 2022 | I69: inactive | J69: 2 | K69: annual | L69: https://www.pspifestival.it/ | M69: null | N69: 0 | O69: IT_EN | P69: https://www.instagram.com/pspi_festival/?hl=it | Q69: https://www.facebook.com/p/Pspi-festival-100084339304483/ | R69: 7 | S69: non-profit | T69: 0 | U69: 1 | V69: 1 | W69: 1 | X69: 1 | Y69: 0 | Z69: 1 | AB69: 0 | AC69: 0 | AD69: 0 | AE69: museum_gallery | AF69: free | AG69: 0
A70: FEST000076 | B70: DMF - Dalmine Manifestazioni Fotografiche | C70: Dalmine | D70: {=XLOOKUP(C70,Locations!A:A,Locations!D:D,"")} -> 3177650 | E70: {=XLOOKUP(C70,Locations!A:A,Locations!E:E,"")} -> Lombardia | F70: {=XLOOKUP(C70,Locations!A:A,Locations!F:F,"")} -> ITC4 | G70: IT | H70: 2012 | I70: active | J70: 9 | K70: annual | L70: https://dmf-ilfestival.it/ | M70: null | N70: 1 | O70: IT_ONLY | P70: null | Q70: https://www.facebook.com/DalmineManifestazioniFotografiche/ | R70: 6 | S70: mixed | T70: 1 | U70: 0 | V70: 0 | W70: 0 | X70: 1 | Y70: 0 | Z70: 0 | AB70: 0 | AC70: 0 | AD70: 0 | AE70: mixed | AF70: free | AG70: 0
A71: FEST000077 | B71: Isole che Parlano - Festival Internazionale | C71: Palau | D71: {=XLOOKUP(C71,Locations!A:A,Locations!D:D,"")} -> 3171654 | E71: {=XLOOKUP(C71,Locations!A:A,Locations!E:E,"")} -> Sardegna | F71: {=XLOOKUP(C71,Locations!A:A,Locations!F:F,"")} -> ITG2 | G71: IT | H71: 1996 | I71: active | J71: 9 | K71: annual | L71: https://www.isolecheparlano.it/ | M71: null | N71: 1 | O71: IT_ONLY | P71: https://www.instagram.com/isolecheparlano/ | Q71: https://www.facebook.com/isolecheparlano/?locale=it_IT | R71: 8 | S71: non-profit | T71: 1 | U71: 0 | V71: 1 | W71: 1 | X71: 1 | Y71: 1 | Z71: 0 | AB71: 0 | AC71: 1 | AD71: 0 | AE71: mixed | AF71: mixed | AG71: 0 | AH71: Le attività poi si estendono stabilmente anche ai comuni limitrofi (La Maddalena, Arzachena, Luogosanto).
A72: FEST000078 | B72: FASE - Festival di Arti Visive a Sud Est | C72: Otranto | D72: {=XLOOKUP(C72,Locations!A:A,Locations!D:D,"")} -> 3171785 | E72: {=XLOOKUP(C72,Locations!A:A,Locations!E:E,"")} -> Puglia | F72: {=XLOOKUP(C72,Locations!A:A,Locations!F:F,"")} -> ITF4 | G72: IT | H72: 2024 | I72: active | J72: 24 | K72: annual | L72: https://fa-se.it/ | M72: null | N72: 1 | O72: IT_EN | P72: https://www.instagram.com/fase_festival/ | Q72: https://www.facebook.com/profile.php?id=61558633691782&locale=fa_IR | R72: 9 | S72: non-profit | T72: 1 | U72: 1 | V72: 1 | W72: 1 | X72: 1 | Y72: 1 | Z72: 0 | AB72: 0 | AC72: 0 | AD72: 1 | AE72: public_space | AF72: free | AG72: 0
A73: FEST000079 | B73: Ronciglione Foto Festival | C73: Ronciglione | D73: {=XLOOKUP(C73,Locations!A:A,Locations!D:D,"")} -> 3169010 | E73: {=XLOOKUP(C73,Locations!A:A,Locations!E:E,"")} -> Lazio | F73: {=XLOOKUP(C73,Locations!A:A,Locations!F:F,"")} -> ITI4 | G73: IT | H73: 2024 | I73: inactive | J73: 4 | K73: annual | L73: null | M73: https://fiaf.net/lazio/ronciglione-foto-festival-2025/ | N73: 0 | O73: IT_ONLY | P73: https://www.instagram.com/ronciglione_foto_festival/ | Q73: https://www.facebook.com/p/Ronciglione-Foto-Festival-61558593723336/?locale=it_IT | R73: 4 | S73: non-profit | T73: 0 | U73: 0 | V73: 0 | W73: 0 | X73: 1 | Y73: 0 | Z73: 0 | AB73: 0 | AC73: 0 | AD73: 0 | AE73: mixed | AF73: free | AG73: 0
A74: FEST000080 | B74: Festival Tank - Immagine Analogica | C74: Apecchio | D74: {=XLOOKUP(C74,Locations!A:A,Locations!D:D,"")} -> 3182992 | E74: {=XLOOKUP(C74,Locations!A:A,Locations!E:E,"")} -> Marche | F74: {=XLOOKUP(C74,Locations!A:A,Locations!F:F,"")} -> ITI3 | G74: IT | H74: 2022 | I74: inactive | J74: 2 | K74: annual | L74: https://www.tankimmagineanalogica.com/#call | M74: null | N74: 0 | O74: IT_ONLY | P74: null | Q74: null | R74: 2 | S74: non-profit | T74: 0 | U74: 1 | V74: 0 | W74: 0 | X74: 1 | Y74: 0 | Z74: 0 | AB74: 0 | AC74: 0 | AD74: 0 | AE74: historic_site | AF74: free | AG74: 0
A75: FEST000081 | B75: Photobook Mania | C75: Bologna | D75: {=XLOOKUP(C75,Locations!A:A,Locations!D:D,"")} -> 3181928 | E75: {=XLOOKUP(C75,Locations!A:A,Locations!E:E,"")} -> Emilia-Romagna | F75: {=XLOOKUP(C75,Locations!A:A,Locations!F:F,"")} -> ITH5 | G75: IT | H75: 2025 | I75: active | J75: 2 | K75: annual | L75: null | M75: https://phmuseum.com/photobook-mania/2026?l=it | N75: 0 | O75: IT_EN | P75: https://www.instagram.com/photobookmania_/ | Q75: null | R75: 3 | S75: private | T75: 0 | U75: 0 | V75: 0 | W75: 1 | X75: 1 | Y75: 0 | Z75: 1 | AB75: 0 | AC75: 0 | AD75: 1 | AE75: public_space | AF75: free | AG75: 0
A76: FEST000082 | B76: FotogramMi. Festival di Fotografia di Architettura a Milano | C76: Milano | D76: {=XLOOKUP(C76,Locations!A:A,Locations!D:D,"")} -> 6951411 | E76: {=XLOOKUP(C76,Locations!A:A,Locations!E:E,"")} -> Lombardia | F76: {=XLOOKUP(C76,Locations!A:A,Locations!F:F,"")} -> ITC4 | G76: IT | H76: 2025 | I76: inactive | J76: 5 | K76: unknown | L76: null | M76: https://ordinearchitetti.mi.it/it/fotogrammi-festival-di-fotografia-di-architettura-milano | N76: 0 | O76: IT_ONLY | P76: null | Q76: null | R76: 0 | S76: non-profit | T76: 1 | U76: 0 | V76: 0 | W76: 0 | X76: 1 | Y76: 0 | Z76: 0 | AB76: 1 | AC76: 0 | AD76: 0 | AE76: cultural_space | AF76: free | AG76: 0
A77: FEST000083 | B77: Foto Forum Festival | C77: Bolzano | D77: {=XLOOKUP(C77,Locations!A:A,Locations!D:D,"")} -> 3181913 | E77: {=XLOOKUP(C77,Locations!A:A,Locations!E:E,"")} -> Trentino-Alto Adige/Südtirol | F77: {=XLOOKUP(C77,Locations!A:A,Locations!F:F,"")} -> ITH1 | G77: IT | H77: 2026 | I77: active | J77: 49 | K77: unknown | L77: https://foto-forum.it/festival/?lang=it | M77: null | N77: 1 | O77: MULTI | P77: https://www.instagram.com/foto_forum/ | Q77: https://www.facebook.com/Foto-Forum-S%C3%BCdtiroler-Gesellschaft-f%C3%BCr-Fotografie-181261345223322/?fref=ts | R77: 10 | S77: non-profit | T77: 0 | U77: 1 | V77: 1 | X77: 1 | Y77: 0 | Z77: 1 | AB77: 0 | AC77: 0 | AD77: 0 | AE77: cultural_space | AF77: free | AG77: 0 | AI77: 46221
A78: FEST000084 | B78: IMP Festival - International Month of Photojournalism | C78: Trento | D78: {=XLOOKUP(C78,Locations!A:A,Locations!D:D,"")} -> 3165243 | E78: {=XLOOKUP(C78,Locations!A:A,Locations!E:E,"")} -> Trentino-Alto Adige/Südtirol | F78: {=XLOOKUP(C78,Locations!A:A,Locations!F:F,"")} -> ITH2 | G78: IT | H78: 2018 | I78: active | J78: 24 | K78: annual | L78: https://www.impfestival.com/ | M78: null | N78: 1 | O78: IT_EN | P78: https://www.instagram.com/impfestival/ | Q78: https://www.facebook.com/IMPfestivalpadova/ | R78: 9 | S78: non-profit | T78: 1 | U78: 0 | V78: 1 | X78: 1 | Y78: 0 | Z78: 1 | AB78: 0 | AC78: 0 | AD78: 1 | AE78: mixed | AF78: paid | AG78: 0 | AH78: Trento è sede dell'ultima edizione (2027). Il festival si è precedentemente svolto a Padova. | AI78: 46222
A79: FEST000085 | B79: Pergine Foto Festival | C79: Pergine Valsugana | D79: {=XLOOKUP(C79,Locations!A:A,Locations!D:D,"")} -> 3171214 | E79: {=XLOOKUP(C79,Locations!A:A,Locations!E:E,"")} -> Trentino-Alto Adige/Südtirol | F79: {=XLOOKUP(C79,Locations!A:A,Locations!F:F,"")} -> ITH2 | G79: IT | H79: 2026 | I79: active | J79: 2 | K79: annual | L79: null | M79: https://www.fotoamatoripergine.it/pergine-foto-festival-2026/ | N79: 0 | O79: IT_ONLY | R79: 4 | S79: non-profit | T79: 0 | U79: 0 | V79: 0 | X79: 1 | Y79: 0 | Z79: 0 | AA79: 0 | AB79: 0 | AC79: 0 | AD79: 0 | AE79: mixed | AF79: free | AG79: 0 | AI79: 46222
A80: FEST000086 | B80: Venezia Photo | C80: Venezia | D80: {=XLOOKUP(C80,Locations!A:A,Locations!D:D,"")} -> 3175005 | E80: {=XLOOKUP(C80,Locations!A:A,Locations!E:E,"")} -> Veneto | F80: {=XLOOKUP(C80,Locations!A:A,Locations!F:F,"")} -> ITH3 | G80: IT | H80: 2018 | I80: active | J80: 4 | K80: annual | L80: https://veneziaphoto.org/it | M80: null | N80: 1 | O80: MULTI | P80: https://www.instagram.com/veneziaphotofestival | Q80: https://www.facebook.com/veneziaphotomasterclass/ | R80: 10 | S80: mixed | T80: 1 | U80: 0 | V80: 1 | X80: 1 | Y80: 0 | Z80: 1 | AB80: 0 | AC80: 0 | AD80: 0 | AE80: historic_site | AF80: paid | AG80: 0 | AI80: 46222
A81: FEST000087 | B81: NARNIMMAGINARIA | C81: Narni | D81: {=XLOOKUP(C81,Locations!A:A,Locations!D:D,"")} -> 3172377 | E81: {=XLOOKUP(C81,Locations!A:A,Locations!E:E,"")} -> Umbria | F81: {=XLOOKUP(C81,Locations!A:A,Locations!F:F,"")} -> ITI2 | G81: IT | H81: unknown | I81: active | J81: 10 | K81: annual | L81: https://www.narnimmaginaria.it/ | M81: null | N81: 1 | O81: IT_ONLY | P81: https://www.instagram.com/narnimmaginaria/ | Q81: https://www.facebook.com/search/top?q=associazione%20culturale%20sator | R81: 8 | S81: non-profit | T81: 1 | U81: 0 | V81: 1 | X81: 1 | Y81: 0 | Z81: 1 | AB81: 0 | AC81: 1 | AD81: 1 | AE81: mixed | AF81: free | AG81: 0 | AI81: 46222
A82: FEST000088 | B82: Perugia Social Photo Fest | C82: Perugia | D82: {=XLOOKUP(C82,Locations!A:A,Locations!D:D,"")} -> 3171180 | E82: {=XLOOKUP(C82,Locations!A:A,Locations!E:E,"")} -> Umbria | F82: {=XLOOKUP(C82,Locations!A:A,Locations!F:F,"")} -> ITI2 | G82: IT | H82: 2012 | I82: defunct | J82: 30 | K82: annual | L82: https://www.perugiasocialphotofest.org/ | M82: null | N82: 0 | O82: IT_EN | P82: https://www.instagram.com/perugia_socialphotofest/ | Q82: https://www.facebook.com/perugiasocialphotofest/?locale=it_IT | R82: 7 | S82: non-profit | T82: 0 | U82: 1 | V82: 1 | X82: 1 | Y82: 0 | Z82: 1 | AB82: 0 | AC82: 0 | AD82: 0 | AE82: mixed | AF82: free | AG82: 0 | AI82: 46225
A83: FEST000089 | B83: Spoltore Fotofestival Naturalistico-Umanistico | C83: Spoltore | D83: {=XLOOKUP(C83,Locations!A:A,Locations!D:D,"")} -> 3166235 | E83: {=XLOOKUP(C83,Locations!A:A,Locations!E:E,"")} -> Abruzzo | F83: {=XLOOKUP(C83,Locations!A:A,Locations!F:F,"")} -> ITF1 | G83: IT | H83: 2024 | I83: active | J83: 2 | K83: annual | L83: null | M83: https://www.festivalinitalia.it/festival/spoltore-fotofestival-naturalistico-umanistico/2025 | N83: 0 | O83: IT_ONLY | R83: 4 | S83: non-profit | T83: 0 | U83: 0 | V83: 0 | X83: 1 | Y83: 0 | Z83: 0 | AB83: 0 | AC83: 0 | AD83: 1 | AE83: mixed | AF83: free | AG83: 1 | AI83: 46225
A84: FEST000090 | B84: BioPhotoFestival - International Nature Photo Festival | C84: Maniago | D84: {=XLOOKUP(C84,Locations!A:A,Locations!D:D,"")} -> 3174084 | E84: {=XLOOKUP(C84,Locations!A:A,Locations!E:E,"")} -> Friuli-Venezia Giulia | F84: {=XLOOKUP(C84,Locations!A:A,Locations!F:F,"")} -> ITH4 | G84: IT | H84: 2014 | I84: inactive | J84: 2 | K84: annual | L84: https://www.biophotofestival.it/ | M84: null | N84: 0 | O84: IT_ONLY | P84: https://www.instagram.com/biophotofestival | Q84: https://www.facebook.com/BioPhotoFestival | R84: 6 | S84: non-profit | T84: 1 | U84: 1 | V84: 0 | X84: 1 | Y84: 0 | Z84: 1 | AB84: 0 | AC84: 0 | AD84: 1 | AE84: cultural_space | AF84: free | AG84: 1 | AI84: 46225
A85: FEST000091 | B85: Festival Internazionale della Fotografia di Zoagli | C85: Zoagli | D85: {=XLOOKUP(C85,Locations!A:A,Locations!D:D,"")} -> 3163859 | E85: {=XLOOKUP(C85,Locations!A:A,Locations!E:E,"")} -> Liguria | F85: {=XLOOKUP(C85,Locations!A:A,Locations!F:F,"")} -> ITC3 | G85: IT | H85: 2024 | I85: active | J85: 4 | K85: annual | L85: https://festivalintdellafotografia.com/index.html | M85: null | N85: 1 | O85: IT_ONLY | P85: https://www.instagram.com/festivalintdellafotografia/ | Q85: https://www.facebook.com/share/16msZjtmwe/?mibextid=wwXIfr | R85: 8 | S85: non-profit | T85: 0 | U85: 0 | V85: 0 | X85: 1 | Y85: 0 | Z85: 0 | AA85: 0 | AB85: 0 | AC85: 0 | AD85: 1 | AE85: historic_site | AF85: free | AG85: 1 | AI85: 46225
A86: FEST000092 | B86: Sanremo Photo Fest | C86: Sanremo | D86: {=XLOOKUP(C86,Locations!A:A,Locations!D:D,"")} -> 3167777 | E86: {=XLOOKUP(C86,Locations!A:A,Locations!E:E,"")} -> Liguria | F86: {=XLOOKUP(C86,Locations!A:A,Locations!F:F,"")} -> ITC3 | G86: IT | H86: 2023 | I86: active | J86: 3 | K86: annual | L86: https://www.sanremophotofest.com/ | M86: null | N86: 1 | O86: IT_ONLY | P86: https://www.instagram.com/sanremophotofest/ | Q86: https://www.facebook.com/SanremoPhotoFest/ | R86: 8 | S86: non-profit | T86: 0 | U86: 0 | V86: 0 | X86: 1 | Y86: 0 | Z86: 1 | AB86: 0 | AC86: 0 | AD86: 0 | AE86: historic_site | AF86: unknown | AG86: 0 | AI86: 46225
A87: FEST000093 | B87: Appennino Foto Festival | C87: Belforte del Chienti | D87: {=XLOOKUP(C87,Locations!A:A,Locations!D:D,"")} -> 3182238 | E87: {=XLOOKUP(C87,Locations!A:A,Locations!E:E,"")} -> Marche | F87: {=XLOOKUP(C87,Locations!A:A,Locations!F:F,"")} -> ITI3 | G87: IT | H87: 2019 | I87: active | J87: unknown | K87: annual | L87: https://www.appenninofotofestival.com/ | M87: null | N87: 1 | O87: IT_ONLY | P87: https://www.instagram.com/axiom_themes/ | Q87: https://www.facebook.com/AxiomThemes | R87: 8 | S87: non-profit | T87: 1 | U87: 1 | V87: 1 | X87: 1 | Y87: 0 | Z87: 0 | AB87: 0 | AC87: 0 | AD87: 1 | AE87: mixed | AF87: unknown | AG87: 1 | AH87: Comune principale di riferimento (MC). Il festival coinvolge però più comuni dell’are | AI87: 46225
A88: FEST000094 | B88: Festival di Fotografia a Capri | C88: Capri | D88: {=XLOOKUP(C88,Locations!A:A,Locations!D:D,"")} -> 3180630 | E88: {=XLOOKUP(C88,Locations!A:A,Locations!E:E,"")} -> Campania | F88: {=XLOOKUP(C88,Locations!A:A,Locations!F:F,"")} -> ITF3 | G88: IT | H88: 2009 | I88: active | J88: 33 | K88: annual | L88: null | M88: https://fondazionecapri.org/?p=7405 | N88: 0 | O88: IT_ONLY | R88: 4 | S88: non-profit | T88: 0 | U88: 1 | V88: 0 | X88: 1 | Y88: 0 | Z88: 0 | AA88: 0 | AB88: 0 | AC88: 0 | AD88: 0 | AE88: historic_site | AF88: unknown | AG88: 0 | AI88: 46225
A89: FEST000095 | B89: Senigallia Fotografia | C89: Senigallia | D89: {=XLOOKUP(C89,Locations!A:A,Locations!D:D,"")} -> 3166740 | E89: {=XLOOKUP(C89,Locations!A:A,Locations!E:E,"")} -> Marche | F89: {=XLOOKUP(C89,Locations!A:A,Locations!F:F,"")} -> ITI3 | G89: IT | H89: 2026 | I89: active | J89: 15 | K89: unknown | L89: null | M89: https://www.feelsenigallia.it/eventi/senigallia-fotografia-2026/ | N89: 0 | O89: IT_ONLY | R89: 4 | S89: mixed | T89: 0 | U89: 0 | V89: 0 | X89: 1 | Y89: 0 | Z89: 1 | AB89: 0 | AC89: 0 | AD89: 0 | AE89: mixed | AF89: free | AG89: 0 | AI89: 46225
A90: FEST000096 | B90: Macerata Photofestival | C90: Macerata | D90: {=XLOOKUP(C90,Locations!A:A,Locations!D:D,"")} -> 3174380 | E90: {=XLOOKUP(C90,Locations!A:A,Locations!E:E,"")} -> Marche | F90: {=XLOOKUP(C90,Locations!A:A,Locations!F:F,"")} -> ITI3 | G90: IT | H90: 2022 | I90: inactive | J90: 10 | K90: annual | L90: null | M90: https://www.abamc.it/news-didattica/item/4-macerata-photofestival | N90: 0 | O90: IT_ONLY | R90: 4 | S90: non-profit | T90: 0 | U90: 0 | V90: 0 | X90: 1 | Y90: 0 | Z90: 0 | AB90: 0 | AC90: 0 | AD90: 0 | AE90: cultural_space | AF90: unknown | AG90: 0 | AI90: 46225
A91: FEST000097 | B91: Immagina - Festival Internazionale di Fotografia | C91: Lanciano | D91: {=XLOOKUP(C91,Locations!A:A,Locations!D:D,"")} -> 3175173 | E91: {=XLOOKUP(C91,Locations!A:A,Locations!E:E,"")} -> Abruzzo | F91: {=XLOOKUP(C91,Locations!A:A,Locations!F:F,"")} -> ITF1 | G91: IT | H91: unknown | I91: active | J91: 5 | K91: annual | L91: null | M91: https://www.festivalinitalia.it/festival/immagina-festival-internazionale-fotografia-lanciano | N91: 0 | O91: IT_ONLY | R91: 4 | S91: non-profit | T91: 0 | U91: 0 | V91: 0 | X91: 1 | Y91: 0 | Z91: 1 | AB91: 0 | AC91: 0 | AD91: 0 | AE91: museum_gallery | AF91: unknown | AG91: 0 | AI91: 46225
A92: FEST000098 | B92: Pescara Foto Festival | C92: Pescara | D92: {=XLOOKUP(C92,Locations!A:A,Locations!D:D,"")} -> 3171168 | E92: {=XLOOKUP(C92,Locations!A:A,Locations!E:E,"")} -> Abruzzo | F92: {=XLOOKUP(C92,Locations!A:A,Locations!F:F,"")} -> ITF1 | G92: IT | H92: 2024 | I92: inactive | J92: 4 | K92: unknown | L92: null | M92: https://fiaf.net/abruzzo/pescara-foto-festival-1-edizione/ | N92: 0 | O92: IT_ONLY | Q92: https://www.facebook.com/p/Pescara-foto-festival-61557455908399/ | R92: 4 | S92: non-profit | T92: 0 | U92: 0 | V92: 0 | X92: 1 | Y92: 1 | Z92: 0 | AB92: 0 | AC92: 0 | AD92: 0 | AE92: cultural_space | AF92: unknown | AG92: 0 | AI92: 46225
A93: FEST000099 | B93: Castiglion Fiorentino Photo Fest | C93: Castiglion Fiorentino | D93: {=XLOOKUP(C93,Locations!A:A,Locations!D:D,"")} -> 3179405 | E93: {=XLOOKUP(C93,Locations!A:A,Locations!E:E,"")} -> Toscana | F93: {=XLOOKUP(C93,Locations!A:A,Locations!F:F,"")} -> ITI1 | G93: IT | H93: 2022 | I93: active | J93: 17 | K93: annual | L93: https://www.cfpf.eu/ | M93: null | N93: 1 | O93: IT_ONLY | P93: https://www.instagram.com/castiglionfiorentinophotofest/ | Q93: https://www.facebook.com/p/Castiglion-Fiorentino-Photo-Fest-100082194791917/?locale=it_IT | R93: 8 | S93: private | T93: 0 | U93: 0 | V93: 0 | X93: 1 | Y93: 0 | Z93: 1 | AB93: 0 | AC93: 0 | AD93: 0 | AE93: historic_site | AF93: free | AG93: 0 | AI93: 46227
A94: FEST000100 | B94: Lago Photo Fest Alpago | C94: Alpago | D94: {=XLOOKUP(C94,Locations!A:A,Locations!D:D,"")} -> 11287678 | E94: {=XLOOKUP(C94,Locations!A:A,Locations!E:E,"")} -> Veneto | F94: {=XLOOKUP(C94,Locations!A:A,Locations!F:F,"")} -> ITH3 | G94: IT | L94: https://www.lagophotofestalpago.it/ | M94: null | R94: 6 | X94: 1 | AI94: 46227
A95: FEST000101 | B95: Insight Foto Festival | C95: Varese | D95: {=XLOOKUP(C95,Locations!A:A,Locations!D:D,"")} -> 3164699 | E95: {=XLOOKUP(C95,Locations!A:A,Locations!E:E,"")} -> Lombardia | F95: {=XLOOKUP(C95,Locations!A:A,Locations!F:F,"")} -> ITC4 | G95: IT | R95: 6 | X95: 1 | AI95: 46227
A96: FEST000102 | B96: Ancona Foto Festival | C96: Ancona | D96: {=XLOOKUP(C96,Locations!A:A,Locations!D:D,"")} -> 3183089 | E96: {=XLOOKUP(C96,Locations!A:A,Locations!E:E,"")} -> Marche | F96: {=XLOOKUP(C96,Locations!A:A,Locations!F:F,"")} -> ITI3 | G96: IT | R96: 6 | X96: 1 | AI96: 46227
A97: FEST000103 | B97: Brescia Photo Festival | C97: Brescia | D97: {=XLOOKUP(C97,Locations!A:A,Locations!D:D,"")} -> 3181554 | E97: {=XLOOKUP(C97,Locations!A:A,Locations!E:E,"")} -> Lombardia | F97: {=XLOOKUP(C97,Locations!A:A,Locations!F:F,"")} -> ITC4 | G97: IT | R97: 6 | X97: 1 | AI97: 46227
A98: FEST000105 | B98: Wide Photo Fest | C98: Milano | D98: {=XLOOKUP(C98,Locations!A:A,Locations!D:D,"")} -> 6951411 | E98: {=XLOOKUP(C98,Locations!A:A,Locations!E:E,"")} -> Lombardia | F98: {=XLOOKUP(C98,Locations!A:A,Locations!F:F,"")} -> ITC4 | G98: IT | R98: 6 | X98: 1 | AI98: 46227
A99: FEST000106 | B99: FotoGrafia. Festival internazionale di Roma | C99: Roma | D99: {=XLOOKUP(C99,Locations!A:A,Locations!D:D,"")} -> 8957247 | E99: {=XLOOKUP(C99,Locations!A:A,Locations!E:E,"")} -> Lazio | F99: {=XLOOKUP(C99,Locations!A:A,Locations!F:F,"")} -> ITI4 | G99: IT | H99: 2002 | I99: defunct | R99: 6 | X99: 1 | AI99: 46227
A100: FEST000107 | B100: BìFoto - Festival della Fotografia in Sardegna | C100: Mogoro | D100: {=XLOOKUP(C100,Locations!A:A,Locations!D:D,"")} -> 2524116 | E100: {=XLOOKUP(C100,Locations!A:A,Locations!E:E,"")} -> Sardegna | F100: {=XLOOKUP(C100,Locations!A:A,Locations!F:F,"")} -> ITG2 | G100: IT | H100: 2011 | I100: active | K100: annual | L100: https://www.bifotofest.it/ | M100: null | N100: 1 | O100: IT_ONLY | P100: https://www.instagram.com/bifotofest?igsh=b2ZtY2t5NTVmODhw | Q100: https://www.facebook.com/share/1JfPyv153j/ | R100: 8 | S100: private | T100: 1 | U100: 1 | V100: 0 | X100: 1 | AE100: public_space | AF100: free | AI100: 46227
...

Sheet CODEBOOK
A1: class | B1: variable_name | C1: description | D1: data_type | E1: values | F1: coding_rules | G1: source
A2: IDENTITY | B2: festival_id | C2: Identificativo univoco del festival | D2: Stringa | E2: Formato: FEST000001 | F2: Assegnare un identificativo univoco progressivo secondo il formato FEST000001. | G2: -
B3: festival_name | C3: Denominazione ufficiale del festival | D3: Stringa | E3: Testo libero | F3: Utilizzare la denominazione ufficiale del festival; evitare sottotitoli o varianti non costanti tra le fonti. | G3: -
A4: LOCATION | B4: city_name | C4: Comune principale di svolgimento del festival | D4: Stringa | E4: Denominazione ufficiale ISTAT del comune | F4: Inserire esclusivamente il comune principale di svolgimento. Nei casi di festival multi-sede o itineranti utilizzare la sede legale o l'hub organizzativo principale e documentare eventuali eccezioni nella variabile notes. | G4: ISTAT, Codici delle unità amministrative. Aggiornamento al 21 febbraio 2026, 2026, https://www.istat.it/classificazione/codici-dei-comuni-delle-province-e-delle-regioni/ (ultimo accesso luglio 2026).
B5: city_geonames_id | C5: Identificativo GeoNames associato al comune | D5: Intero | E5: Identificativo GeoNames | F5: Associare l'identificativo GeoNames corrispondente al comune selezionato. | G5: GeoNames, GeoNames Data, IT.zip, 2026, https://download.geonames.org/export/dump/ (ultimo accesso luglio 2026).
B6: region | C6: Regione italiana di riferimento del festival | D6: Stringa | E6: Denominazione ufficiale ISTAT della regione | F6: Derivare automaticamente dalla città selezionata utilizzando le denominazioni ufficiali ISTAT. | G6: ISTAT, Codici delle unità amministrative. Aggiornamento al 21 febbraio 2026, 2026, https://www.istat.it/classificazione/codici-dei-comuni-delle-province-e-delle-regioni/ (ultimo accesso luglio 2026).
B7: region_nuts | C7: Codice NUTS2 della regione | D7: Stringa | E7: Codice Eurostat NUTS2 | F7: Associare il codice Eurostat NUTS2 corrispondente alla regione. | G7: Eurostat, NUTS - NOMENCLATURE OF TERRITORIAL UNITS FOR STATISTICS. Overview, s.d., https://ec.europa.eu/eurostat/web/nuts (ultimo accesso luglio 2026).
B8: country_iso | C8: Codice ISO 3166-1 alpha-2 del Paese | D8: Stringa | E8: Codice ISO 3166-1 alpha-2 | F8: Utilizzare il codice ISO 3166-1 alpha-2 del Paese di svolgimento. Nel presente dataset il valore è sempre IT. | G8: ISO, ISO 3166. Country Codes, s.d.-a, https://www.iso.org/iso-3166-country-codes.html (ultimo accesso luglio 2026).
A9: TIME | B9: first_edition_year | C9: Anno della prima edizione del festival | D9: Intero | E9: anno / unknown | F9: Estrarre da sito ufficiale o fonti affidabili. Se non presente o non affidabile, inserire unknown. | G9: YOUROPE – The European Festival Association, ILMC, European Festival Report 2025, Drury J. (a cura di), IQ Magazine, 2026, https://yourope.org/know-how/european-festival-report-2025-out-now/ (ultimo accesso luglio 2026).
B10: festival_status | C10: Stato di attività del festival | D10: Enumerazione | E10: active / inactive / defunct / unknown | F10: - active: almeno un'edizione negli ultimi 18-24 mesi oppure annuncio ufficiale della prossima edizione (date o open call) - inactive: il festival non ha svolto edizioni negli ultimi 2 anni, ma non ha dichiarato la chiusura e i canali social/sito sono ancora online (anche se fermi) - defunct: esiste una dichiarazione ufficiale di chiusura - unknown: mancanza di dati verificabili o presenza di informazioni contrastanti | G10: YOUROPE – The European Festival Association, ILMC, European Festival Report 2025, Drury J. (a cura di), IQ Magazine, 2026, https://yourope.org/know-how/european-festival-report-2025-out-now/ (ultimo accesso luglio 2026).
B11: duration_days | C11: Durata dell'edizione più recente del festival, espressa in giorni | D11: Intero | E11: numero / unknown | F11: Si contano sia il giorno d'inizio che quello di fine (data fine - data inizio + 1) - Se il festival prevede un evento inaugurale seguito da mostre aperte al pubblico, considerare l'intero periodo di apertura - Vengono contati i giorni di durata dell'edizione più recente - unknown: se non vi sono date precise | G11: YOUROPE – The European Festival Association, ILMC, European Festival Report 2025, Drury J. (a cura di), IQ Magazine, 2026, https://yourope.org/know-how/european-festival-report-2025-out-now/ (ultimo accesso luglio 2026).
B12: recurrence | C12: Periodicità della manifestazione | D12: Enumerazione | E12: annual / biennial / mixed / unknown | F12: - annual: il festival si svolge regolarmente ogni anno - biennial: il festival si svolge regolarmente ogni due anni - mixed: il festival ha cambiato cadenza nel tempo - unknown: non vi sono sufficienti informazioni | G12: YOUROPE – The European Festival Association, ILMC, European Festival Report 2025, Drury J. (a cura di), IQ Magazine, 2026, https://yourope.org/know-how/european-festival-report-2025-out-now/ (ultimo accesso luglio 2026).
A13: DIGITAL PRESENCE | B13: website_official | C13: URL del sito web ufficiale del festival, se disponibile | D13: Stringa | E13: URL / null | F13: Inserire esclusivamente il sito web ufficiale della manifestazione. | G13: European Commission, Creative Europe 2021-2022: Monitoring report, Luxembourg, Publications Office of the European Union, 2023, https://doi.org/10.2759/561008.
B14: website_secondary | C14: URL di una fonte web secondaria di riferimento | D14: Stringa | E14: URL / null | F14: Compilare solo in assenza di un sito web ufficiale. | G14: European Commission, Creative Europe 2021-2022: Monitoring report, Luxembourg, Publications Office of the European Union, 2023, https://doi.org/10.2759/561008.
B15: website_active | C15: Stato di attività del sito web ufficiale | D15: Booleano | E15: 0 / 1 | F15: 1 = sito ufficiale raggiungibile e aggiornato 0 = sito non raggiungibile, non aggiornato o assente | G15: European Commission, Creative Europe 2021-2022: Monitoring report, Luxembourg, Publications Office of the European Union, 2023, https://doi.org/10.2759/561008.
B16: website_languages | C16: Lingue disponibili nel sito web ufficiale/secondario | D16: Enumerazione | E16: IT_EN / IT_ONLY / MULTI | F16: IT_EN: disponibile lingua inglese oltre l'italiano IT_ONLY: solo lingua italiana MULTI: disponibili altre lingue, oltre inglese e italiano | G16: European Commission, Creative Europe 2021-2022: Monitoring report, Luxembourg, Publications Office of the European Union, 2023, https://doi.org/10.2759/561008.
B17: instagram | C17: URL del profilo Instagram ufficiale | D17: Stringa | E17: URL / null | F17: Inserire solo profilo ufficiale | G17: European Commission, Creative Europe 2021-2022: Monitoring report, Luxembourg, Publications Office of the European Union, 2023, https://doi.org/10.2759/561008.
B18: facebook | C18: URL del profilo Facebook ufficiale | D18: Stringa | E18: URL / null | F18: Inserire solo profilo ufficiale | G18: European Commission, Creative Europe 2021-2022: Monitoring report, Luxembourg, Publications Office of the European Union, 2023, https://doi.org/10.2759/561008.
B19: digital_presence_score | C19: Indicatore composito del livello di presenza digitale del festival | D19: Intero | E19: da 0 a 10 compresi | F19: Website (Max 4pt): - Sito ufficiale presente: +2pt - Sito ufficiale ATTIVO (website_active = 1): +2pt Social (Max 4pt): - Instagram dedicato = +2pt - Facebook dedicato = +2pt Lingue (Max 2pt): - Multilingue = +2pt - Inglese (su sito attivo o secondario) = +1pt - Solo italiano = +0pt | G19: European Commission, Special Eurobarometer 562: Europeans’ attitudes towards culture, (Report No. SP562), Luxembourg, Publications Office of the European Union, 2025b, https://doi.org/10.2766/4514147.
A20: ORGANIZATION | B20: organizer_type | C20: Natura giuridica dell'ente organizzatore | D20: Enumerazione | E20: public / private / non_profit / unknown / mixed | F20: - public: quando l'organizzatore è un ente della Pubblica Amministrazione - non_proft: l'organizzatore è associazione culturale, di volontariato, di promozione sociale o fondazione culturale non bancaria - private: l'organizzatore è un'entità commerciale - mixed: co-organizzazione pubblico/privato - unknown: informazione non verificabile | G20: Giorgi L. (a cura di), European Arts Festivals: Cultural Pragmatics and Discursive Identity Frames (Deliverable 3.1, WP3 Main Report, Project EURO-FESTIVAL), European Commission, 2010, https://www.academia.edu/21774168/European_Arts_Festivals_Cultural_Pragmatics_and_Discursive_The_S%C3%B3nar_Festival (ultimo accesso luglio 2026).
B21: has_documented_public_funding | C21: Presenza documentata di finanziamenti pubblici al festival | D21: Booleano | E21: 0 / 1 | F21: 1: vi è evidenza di contributi economici pubblici 0: assenza di evidenze documentate di contributi economici pubblici | G21: Giorgi L. (a cura di), European Arts Festivals: Cultural Pragmatics and Discursive Identity Frames (Deliverable 3.1, WP3 Main Report, Project EURO-FESTIVAL), European Commission, 2010, https://www.academia.edu/21774168/European_Arts_Festivals_Cultural_Pragmatics_and_Discursive_The_S%C3%B3nar_Festival (ultimo accesso luglio 2026).
B22: has_international_call | C22: Presenza di una open call aperta a partecipanti internazionali | D22: Booleano | E22: 0 / 1 | F22: 1: open call aperta a fotografi di ogni nazionalità 0: open call assente oppure riservata a partecipanti italiani | G22: Giorgi L. (a cura di), European Arts Festivals: Cultural Pragmatics and Discursive Identity Frames (Deliverable 3.1, WP3 Main Report, Project EURO-FESTIVAL), European Commission, 2010, https://www.academia.edu/21774168/European_Arts_Festivals_Cultural_Pragmatics_and_Discursive_The_S%C3%B3nar_Festival (ultimo accesso luglio 2026).
B23: has_international_partners | C23: Presenza di partner o sponsor internazionali | D23: Booleano | E23: 0 / 1 | F23: 1: presenza dichiarata di partner, istituzioni, organizzazioni o sponsor internazionali. 0: non sono dichiarati partner o sponsor internazionali, solo italiani | G23: Giorgi L. (a cura di), European Arts Festivals: Cultural Pragmatics and Discursive Identity Frames (Deliverable 3.1, WP3 Main Report, Project EURO-FESTIVAL), European Commission, 2010, https://www.academia.edu/21774168/European_Arts_Festivals_Cultural_Pragmatics_and_Discursive_The_S%C3%B3nar_Festival (ultimo accesso luglio 2026).
A24: CULTURAL DOMAINS | B24: has_photography | C24: Presenza del dominio culturale fotografia nel programma del festival | D24: Booleano | E24: 0 / 1 | F24: 1 = il programma include attività fotografiche (es. mostre, installazioni, workshop, concorsi, portfolio review, incontri con fotografi o altre attività in cui la fotografia costituisce il tema centrale). 0 = la fotografia è presente esclusivamente come documentazione, comunicazione o materiale promozionale, senza una programmazione fotografica. | G24: Bína V., Chantepie P., Deroin V., Frank G., Kommel K., Kotýnek J., Robin P., ESSnet-Culture: European Statistical System Network on Culture. Final Report, Luxembourg, Ministry of Culture / European Commission (Eurostat), 2012.
B25: has_other_visual_arts | C25: Presenza di arti visive diverse dalla fotografia nel programma del festival | D25: Booleano | E25: 0 / 1 | F25: 1 = il programma include almeno un'altra disciplina delle arti visive oltre alla fotografia (es. pittura, scultura, installazione, arte contemporanea, graphic design, illustrazione, incisione). 0 = il programma comprende esclusivamente fotografia oppure elementi espositivi privi di una componente artistica autonoma. La fotografia è codificata separatamente tramite has_photography. | G25: Bína V., Chantepie P., Deroin V., Frank G., Kommel K., Kotýnek J., Robin P., ESSnet-Culture: European Statistical System Network on Culture. Final Report, Luxembourg, Ministry of Culture / European Commission (Eurostat), 2012.
B26: has_books_press | C26: Presenza di attività editoriali nel programma del festival | D26: Booleano | E26: 0 / 1 | F26: 1 = il programma include attività editoriali (es. presentazioni di libri, photobook, book fair, editoria indipendente, incontri con editori, premi dedicati ai libri fotografici). 0 = sono presenti esclusivamente cataloghi del festival, bookshop, materiali informativi o merchandising. | G26: Bína V., Chantepie P., Deroin V., Frank G., Kommel K., Kotýnek J., Robin P., ESSnet-Culture: European Statistical System Network on Culture. Final Report, Luxembourg, Ministry of Culture / European Commission (Eurostat), 2012.
A27: CULTURAL DOMAINS | B27: has_architecture_design | C27: Presenza del dominio culturale architettura e design nel programma del festival | D27: Booleano | E27: 0 / 1 | F27: 1 = il programma include attività dedicate ad architettura o design (es. mostre, workshop, conferenze, sezioni tematiche o partnership con istituzioni del settore). 0 = architettura o design costituiscono esclusivamente il contesto fisico o il soggetto di alcune fotografie, senza rappresentare un tema del programma. | G27: Bína V., Chantepie P., Deroin V., Frank G., Kommel K., Kotýnek J., Robin P., ESSnet-Culture: European Statistical System Network on Culture. Final Report, Luxembourg, Ministry of Culture / European Commission (Eurostat), 2012.
B28: has_performing_arts | C28: Presenza di arti performative nel programma del festival | D28: Booleano | E28: 0 / 1 | F28: 1 = il programma include attività performative (es. teatro, danza, performance artistiche, musica dal vivo o performance interdisciplinari). 0 = sono presenti esclusivamente accompagnamenti musicali, DJ set, eventi sociali o conferenze. | G28: Bína V., Chantepie P., Deroin V., Frank G., Kommel K., Kotýnek J., Robin P., ESSnet-Culture: European Statistical System Network on Culture. Final Report, Luxembourg, Ministry of Culture / European Commission (Eurostat), 2012.
B29: has_audiovisual_multimedia | C29: Presenza di attività appartenenti al dominio audiovisivo e multimediale nel programma del festival | D29: Booleano | E29: 0 / 1 | F29: 1 = il programma include contenuti audiovisivi o multimediali (es. cinema, documentari, videoarte, videoinstallazioni, opere multimediali, installazioni sonore, VR/AR, podcast). 0 = gli strumenti audiovisivi sono utilizzati esclusivamente come supporto tecnico o promozionale. | G29: Bína V., Chantepie P., Deroin V., Frank G., Kommel K., Kotýnek J., Robin P., ESSnet-Culture: European Statistical System Network on Culture. Final Report, Luxembourg, Ministry of Culture / European Commission (Eurostat), 2012.
A30: ACCESSIBILITY & SUSTAINABILITY | B30: venue_type | C30: Tipologia degli spazi che ospitano il festival | D30: Enumerazione | E30: museum_gallery / cultural_space / historic_site / public_space / mixed / unknown | F30: - museum_gallery: musei, gallerie d’arte, pinacoteche e spazi espositivi dedicati alla conservazione o esposizione artistica. - cultural_space: spazi culturali polifunzionali, hub creativi, centri culturali o sedi dedicate ad attività artistiche. - historic_site: luoghi di interesse storico o patrimoniale, quali castelli, palazzi storici, siti archeologici o complessi monumentali. - public_space: spazi pubblici aperti o urbani, quali piazze, strade, parchi o giardini. - mixed: presenza di più tipologie di spazi senza una categoria prevalente. - unknown: tipologia dello spazio non determinabile dalle fonti disponibili. La classificazione considera la funzione prevalente dello spazio ospitante e non esclusivamente le caratteristiche architettoniche. | G30: Alberti V., Cocco C., Consoli S., Montalto V., Panella F., Ontology Engineering to Model the European Cultural Heritage: The Case of Cultural Gems, in Yang X.-S., Sherratt R. S., Dey N., Joshi A. (a cura di), Proceedings of Eighth International Congress on Information and Communication Technology, vol. 696, Singapore, Springer Singapore, 2024, pp. 1–10, https://doi.org/10.1007/978-981-99-3236-8_1.
B31: ticket_policy | C31: Modalità di accesso economico al festival | D31: Enumerazione | E31: free / paid / mixed / unknown | F31: - free: tutte le attività sono ad accesso libero e gratuito - paid: per accedere al corpo principale delle mostre è necessario acquistare un biglietto o un pass - mixed: combinazione di contenuti gratuiti e a pagamento | G31: European Commission, Special Eurobarometer 562: Europeans’ attitudes towards culture, (Report No. SP562), Luxembourg, Publications Office of the European Union, 2025b, https://doi.org/10.2766/4514147.
B32: sustainability_claim | C32: Presenza di dichiarazioni esplicite sull'impegno ambientale del festival | D32: Booleano | E32: 0 / 1 | F32: Attribuire valore 1 solo in presenza di dichiarazioni esplicite relative alla sostenibilità ambientale (es. cambiamento climatico, biodiversità, economia circolare, mobilità sostenibile, Agenda 2030 - SDGs ambientali). | G32: YOUROPE – The European Festival Association, ILMC, European Festival Report 2025, Drury J. (a cura di), IQ Magazine, 2026, https://yourope.org/know-how/european-festival-report-2025-out-now/ (ultimo accesso luglio 2026).
A33: METADATA | B33: notes | C33: Annotazioni qualitative e informazioni aggiuntive sul record | D33: Stringa | E33: Testo libero | F33: Inserire informazioni rilevanti non rappresentabili tramite variabili strutturate, ad esempio: - sedi secondarie; - carattere itinerante del festival; - cambiamenti organizzativi; - informazioni ambigue o non verificabili; - eccezioni metodologiche. | G33: -
B34: record_last_updated | C34: Data dell'ultima revisione del record | D34: Data | E34: Data nel formato ISO 8601: YYYY-MM-DD | F34: Indicare la data dell'ultimo controllo o aggiornamento significativo del record. | G34: -

Sheet Locations
A1: city | B1: city_geonames_name | C1: city_istat_code | D1: city_geonames_id | E1: region | F1: regione_nuts | G1: country | H1: country_iso
A2: Agliè | C2: 1001 | D2: {=IF(A2:A7894="","",XLOOKUP(A2:A7894,GEONAMES!A:A,GEONAMES!B:B,""))} | E2: Piemonte | F2: ITC1
A3: Airasca | C3: 1002 | D3: 3183380 | E3: Piemonte | F3: ITC1
A4: Ala di Stura | C4: 1003 | D4: 3183371 | E4: Piemonte | F4: ITC1
A5: Albiano d'Ivrea | C5: 1004 | D5: 3183322 | E5: Piemonte | F5: ITC1
A6: Almese | C6: 1006 | E6: Piemonte | F6: ITC1
A7: Alpette | C7: 1007 | D7: 3183198 | E7: Piemonte | F7: ITC1
A8: Alpignano | C8: 1008 | D8: 3183187 | E8: Piemonte | F8: ITC1
A9: Andezeno | C9: 1009 | D9: 3183081 | E9: Piemonte | F9: ITC1
A10: Andrate | C10: 1010 | D10: 3183077 | E10: Piemonte | F10: ITC1
A11: Angrogna | C11: 1011 | D11: 6535055 | E11: Piemonte | F11: ITC1
A12: Arignano | C12: 1012 | D12: 3182846 | E12: Piemonte | F12: ITC1
A13: Avigliana | C13: 1013 | D13: 3182634 | E13: Piemonte | F13: ITC1
A14: Azeglio | C14: 1014 | D14: 3182615 | E14: Piemonte | F14: ITC1
A15: Bairo | C15: 1015 | D15: 6535053 | E15: Piemonte | F15: ITC1
A16: Balangero | C16: 1016 | D16: 3182466 | E16: Piemonte | F16: ITC1
A17: Baldissero Canavese | C17: 1017 | D17: 6535054 | E17: Piemonte | F17: ITC1
A18: Baldissero Torinese | C18: 1018 | D18: 3182461 | E18: Piemonte | F18: ITC1
... A48: Cambiano | C48: 1048 | D48: 3181111 | E48: Piemonte | F48: ITC1
A49: Campiglione Fenile | C49: 1049 | E49: Piemonte | F49: ITC1
A50: Candia Canavese | C50: 1050 | D50: 3180868 | E50: Piemonte | F50: ITC1
A51: Candiolo | C51: 1051 | D51: 3180861 | E51: Piemonte | F51: ITC1
A52: Canischio | C52: 1052 | D52: 3180835 | E52: Piemonte | F52: ITC1
A53: Cantalupa | C53: 1053 | D53: 6535265 | E53: Piemonte | F53: ITC1
A54: Cantoira | C54: 1054 | D54: 3180766 | E54: Piemonte | F54: ITC1
A55: Caprie | C55: 1055 | D55: 3180621 | E55: Piemonte | F55: ITC1
A56: Caravino | C56: 1056 | D56: 3180578 | E56: Piemonte | F56: ITC1
A57: Carema | C57: 1057 | D57: 3180531 | E57: Piemonte | F57: ITC1
A58: Carignano | C58: 1058 | D58: 3180511 | E58: Piemonte | F58: ITC1
A59: Carmagnola | C59: 1059 | D59: 3180496 | E59: Piemonte | F59: ITC1
A60: Casalborgone | C60: 1060 | D60: 3180245 | E60: Piemonte | F60: ITC1
A61: Cascinette d'Ivrea | C61: 1061 | D61: 3179958 | E61: Piemonte | F61: ITC1
... A85: Cinzano | C85: 1085 | D85: 3178662 | E85: Piemonte | F85: ITC1
A86: Ciriè | C86: 1086 | E86: Piemonte | F86: ITC1
A87: Claviere | C87: 1087 | D87: 3178550 | E87: Piemonte | F87: ITC1
A88: Coassolo Torinese | C88: 1088 | D88: 6534296 | E88: Piemonte | F88: ITC1
A89: Coazze | C89: 1089 | D89: 3178536 | E89: Piemonte | F89: ITC1
A90: Collegno | C90: 1090 | D90: 3178388 | E90: Piemonte | F90: ITC1
A91: Colleretto Castelnuovo | C91: 1091 | D91: 6535270 | E91: Piemonte | F91: ITC1
A92: Colleretto Giacosa | C92: 1092 | D92: 6535271 | E92: Piemonte | F92: ITC1
A93: Condove | C93: 1093 | D93: 3178198 | E93: Piemonte | F93: ITC1
A94: Corio | C94: 1094 | D94: 3178093 | E94: Piemonte | F94: ITC1
A95: Cossano Canavese | C95: 1095 | D95: 6535272 | E95: Piemonte | F95: ITC1
A96: Cuceglio | C96: 1096 | D96: 3177726 | E96: Piemonte | F96: ITC1
A97: Cumiana | C97: 1097 | D97: 3177704 | E97: Piemonte | F97: ITC1
A98: Cuorgnè | C98: 1098 | E98: Piemonte | F98: ITC1
A99: Druento | C99: 1099 | D99: 3177471 | E99: Piemonte | F99: ITC1
A100: Exilles | C100: 1100 | D100: 3177326 | E100: Piemonte | F100: ITC1
A101: Favria | C101: 1101 | D101: 3177140 | E101: Piemonte | F101: ITC1
A102: Feletto | C102: 1102 | D102: 3177127 | E102: Piemonte | F102: ITC1
A103: Fenestrelle | C103: 1103 | D103: 3177112 | E103: Piemonte | F103: ITC1
A104: Fiano | C104: 1104 | D104: 3177047 | E104: Piemonte | F104: ITC1
A105: Fiorano Canavese | C105: 1105 | D105: 6535273 | E105: Piemonte | F105: ITC1
A106: Foglizzo | C106: 1106 | D106: 3176869 | E106: Piemonte | F106: ITC1
A107: Forno Canavese | C107: 1107 | D107: 3176687 | E107: Piemonte | F107: ITC1
A108: Frassinetto | C108: 1108 | D108: 3176577 | E108: Piemonte | F108: ITC1
A109: Front | C109: 1109 | D109: 3176521 | E109: Piemonte | F109: ITC1
A110: Frossasco | C110: 1110 | D110: 6535393 | E110: Piemonte | F110: ITC1
... A136: Lombriasco | C136: 1136 | D136: 6535808 | E136: Piemonte | F136: ITC1
A137: Loranzè | C137: 1137 | E137: Piemonte | F137: ITC1
A138: Luserna San Giovanni | C138: 1139 | E138: Piemonte | F138: ITC1
A139: Lusernetta | C139: 1140 | D139: 6535809 | E139: Piemonte | F139: ITC1
A140: Lusigliè | C140: 1141 | E140: Piemonte | F140: ITC1
A141: Macello | C141: 1142 | D141: 6535403 | E141: Piemonte | F141: ITC1
A142: Maglione | C142: 1143 | D142: 6535810 | E142: Piemonte | F142: ITC1
A143: Marentino | C143: 1144 | D143: 6535811 | E143: Piemonte | F143: ITC1
A144: Massello | C144: 1145 | D144: 3173751 | E144: Piemonte | F144: ITC1
A145: Mathi | C145: 1146 | D145: 3173714 | E145: Piemonte | F145: ITC1
A146: Mattie | C146: 1147 | D146: 6535404 | E146: Piemonte | F146: ITC1
A147: Mazzè | C147: 1148 | E147: Piemonte | F147: ITC1
A148: Meana di Susa | C148: 1149 | D148: 6535812 | E148: Piemonte | F148: ITC1
A149: Mercenasco | C149: 1150 | D149: 3173557 | E149: Piemonte | F149: ITC1
A150: Mezzenile | C150: 1152 | D150: 6535813 | E150: Piemonte | F150: ITC1
A151: Mombello di Torino | C151: 1153 | D151: 6535406 | E151: Piemonte | F151: ITC1
A152: Mompantero | C152: 1154 | D152: 6534307 | E152: Piemonte | F152: ITC1
A153: Monastero di Lanzo | C153: 1155 | D153: 6535407 | E153: Piemonte | F153: ITC1
A154: Moncalieri | C154: 1156 | D154: 3173180 | E154: Piemonte | F154: ITC1
A155: Moncenisio | C155: 1157 | D155: 6535408 | E155: Piemonte | F155: ITC1
A156: Montaldo Torinese | C156: 1158 | D156: 6535409 | E156: Piemonte | F156: ITC1
A157: Montalenghe | C157: 1159 | D157: 3173088 | E157: Piemonte | F157: ITC1
A158: Montalto Dora | C158: 1160 | D158: 3173081 | E158: Piemonte | F158: ITC1
A159: Montanaro | C159: 1161 | D159: 3173074 | E159: Piemonte | F159: ITC1
... A179: Pavone Canavese | C179: 1181 | D179: 3171358 | E179: Piemonte | F179: ITC1
A180: Pecetto Torinese | C180: 1183 | E180: Piemonte | F180: ITC1
A181: Perosa Argentina | C181: 1184 | D181: 3171193 | E181: Piemonte | F181: ITC1
A182: Perosa Canavese | C182: 1185 | D182: 6535411 | E182: Piemonte | F182: ITC1
A183: Perrero | C183: 1186 | D183: 3171191 | E183: Piemonte | F183: ITC1
A184: Pertusio | C184: 1187 | D184: 6535412 | E184: Piemonte | F184: ITC1
A185: Pessinetto | C185: 1188 | D185: 3171118 | E185: Piemonte | F185: ITC1
A186: Pianezza | C186: 1189 | D186: 3170978 | E186: Piemonte | F186: ITC1
A187: Pinasca | C187: 1190 | E187: Piemonte | F187: ITC1
A188: Pinerolo | C188: 1191 | D188: 3170694 | E188: Piemonte | F188: ITC1
A189: Pino Torinese | C189: 1192 | D189: 6534250 | E189: Piemonte | F189: ITC1
A190: Piobesi Torinese | C190: 1193 | D190: 3170678 | E190: Piemonte | F190: ITC1
A191: Piossasco | C191: 1194 | D191: 3170659 | E191: Piemonte | F191: ITC1
A192: Piscina | C192: 1195 | D192: 6535414 | E192: Piemonte | F192: ITC1
A193: Piverone | C193: 1196 | D193: 6535415 | E193: Piemonte | F193: ITC1
A194: Poirino | C194: 1197 | D194: 3170408 | E194: Piemonte | F194: ITC1
A195: Pomaretto | C195: 1198 | D195: 3170351 | E195: Piemonte | F195: ITC1
A196: Pont Canavese | C196: 1199 | D196: 3170316 | E196: Piemonte | F196: ITC1
...

Sheet GEONAMES
A1: city | B1: geonames_id
A2: Corigliano-Rossano | B2: 12032199
A3: Neive | B3: 6536417
A4: Alpago | B4: 11287678
A5: Fiumicello Villa Vicentina | B5: 12032187
A6: Colognole | B6: 781059
A7: Casale Sant'Antonio | B7: 781060
A8: Zungti | B8: 2522676
A9: Zumpano | B9: 2522677
A10: Zona | B10: 2522679
A11: Zinga | B11: 2522681
A12: Zerfaliu | B12: 2522683
A13: Zeppara | B13: 2522684
... A32046: Zucchi | B32046: 8960423
A32047: FALSE | B32047: 8960424
A32048: Casalini | B32048: 8960425
A32049: Case Frasson | B32049: 8960426
A32050: Bocca di Serra | B32050: 8960427
A32051: Guizza | B32051: 8960428
A32052: Bobbato | B32052: 8960429
A32053: Volpato | B32053: 8960430
A32054: Rialto | B32054: 8960431
A32055: Zona Buzzaccarina | B32055: 8960432
A32056: Monte Grappa | B32056: 8960433
A32057: Della Croce | B32057: 8960434
A32058: Santa Lucia | B32058: 8960435
A32059: Grottarole | B32059: 8960436
... A58259: Selvavetere | B58259: 13665314

Sheet SCARTATI
A1: FEST000033 | B1: miart | C1: Milano | D1: {=XLOOKUP(C1,Locations!A:A,Locations!D:D,"")} -> 6951411 | E1: {=XLOOKUP(C1,Locations!A:A,Locations!E:E,"")} -> Lombardia | F1: {=XLOOKUP(C1,Locations!A:A,Locations!F:F,"")} -> ITC4 | G1: IT | H1: 1996 | J1: 3 giorni | K1: annual | L1: http://www.miart.it/ | P1: https://www.instagram.com/miartmilano/?hl=it | Q1: https://www.facebook.com/miart.milano/?locale=it_IT | R1: 6 | X1: 1
A2: FEST000037 | B2: Genius Loci | C2: Latina | D2: {=XLOOKUP(C2,Locations!A:A,Locations!D:D,"")} -> 3175058 | E2: {=XLOOKUP(C2,Locations!A:A,Locations!E:E,"")} -> Lazio | F2: {=XLOOKUP(C2,Locations!A:A,Locations!F:F,"")} -> ITI4 | G2: IT | H2: 2025 | J2: 7 giorni | K2: annual | M2: https://openhublazio.it/it/open-calls/genius-loci | R2: 0 | X2: 1
A3: FEST000039 | B3: Pulcinella Film Fest - Festival della Commedia | C3: Acerra | D3: {=XLOOKUP(C3,Locations!A:A,Locations!D:D,"")} -> 3183541 | E3: {=XLOOKUP(C3,Locations!A:A,Locations!E:E,"")} -> Campania | F3: {=XLOOKUP(C3,Locations!A:A,Locations!F:F,"")} -> ITF3 | G3: IT | H3: 2018 | J3: 7 giorni | K3: annual | L3: https://www.festivaldellacommedia.it/it/ | P3: https://www.instagram.com/festivaldellacommedia/ | Q3: https://www.facebook.com/festivaldellacommedia/?locale=it_IT | R3: 6 | X3: 1
A4: FEST000041 | B4: Festival N*Stories | C4: Altamura | D4: {=XLOOKUP(C4,Locations!A:A,Locations!D:D,"")} -> 3183178 | E4: {=XLOOKUP(C4,Locations!A:A,Locations!E:E,"")} -> Puglia | F4: {=XLOOKUP(C4,Locations!A:A,Locations!F:F,"")} -> ITF4 | G4: IT | H4: 2018 | J4: 7 giorni | K4: annual | L4: https://www.festivalnstories.it/ | P4: https://www.instagram.com/festivalnstories/ | Q4: https://www.facebook.com/festivalnstories | R4: 6 | X4: 1
A5: FEST000042 | B5: Festival della Comunicazione e del Cinema Archeologico | C5: Licodia Eubea | D5: {=XLOOKUP(C5,Locations!A:A,Locations!D:D,"")} -> 2524392 | E5: {=XLOOKUP(C5,Locations!A:A,Locations!E:E,"")} -> Sicilia | F5: {=XLOOKUP(C5,Locations!A:A,Locations!F:F,"")} -> ITG1 | G5: IT | H5: 2011 | J5: 7 giorni | K5: annual | L5: https://www.rassegnalicodia.it/ | P5: https://instagram.com/festivallicodiaeubea | Q5: https://www.facebook.com/festivallicodiaeubea | R5: 6 | X5: 1
A6: FEST000045 | B6: Alcart Festival | C6: Alcamo | D6: {=XLOOKUP(C6,Locations!A:A,Locations!D:D,"")} -> 2525755 | E6: {=XLOOKUP(C6,Locations!A:A,Locations!E:E,"")} -> Sicilia | F6: {=XLOOKUP(C6,Locations!A:A,Locations!F:F,"")} -> ITG1 | G6: IT | H6: 2023 | J6: 5 giorni | K6: annual | M6: https://www.comune.alcamo.tp.it/it/eventi/alcart | P6: https://www.instagram.com/alcartfestival/ | Q6: https://www.facebook.com/alcartfestival/?locale=it_IT | R6: 4 | X6: 1
A7: FEST000046 | B7: AbitiAmo la Terra | C7: Piossasco | D7: {=XLOOKUP(C7,Locations!A:A,Locations!D:D,"")} -> 3170659 | E7: {=XLOOKUP(C7,Locations!A:A,Locations!E:E,"")} -> Piemonte | F7: {=XLOOKUP(C7,Locations!A:A,Locations!F:F,"")} -> ITC1 | G7: IT | H7: 2014 | J7: 6 giorni | K7: annual | M7: https://www.amicidijoaquimgomes.it/2025/05/24/abitiamo-la-terra-festa-brasiliana-2025/ | R7: 0 | X7: 1
A8: FEST000047 | B8: Between Land and Sea | C8: Palermo | D8: {=XLOOKUP(C8,Locations!A:A,Locations!D:D,"")} -> 2523920 | E8: {=XLOOKUP(C8,Locations!A:A,Locations!E:E,"")} -> Sicilia | F8: {=XLOOKUP(C8,Locations!A:A,Locations!F:F,"")} -> ITG1 | G8: IT | H8: 2021 | J8: 4 giorni | K8: annual | L8: https://www.betweenlandandsea.org/ | P8: https://www.instagram.com/studio_rizoma_/ | Q8: https://www.facebook.com/studiorizomapa | R8: 6 | X8: 1
A9: FEST000050 | B9: SI Fest Off | C9: Verghereto | D9: {=XLOOKUP(C9,Locations!A:A,Locations!D:D,"")} -> 3164550 | E9: {=XLOOKUP(C9,Locations!A:A,Locations!E:E,"")} -> Emilia-Romagna | F9: {=XLOOKUP(C9,Locations!A:A,Locations!F:F,"")} -> ITH5 | G9: IT | H9: 2009 | J9: 3 giorni | K9: annual | M9: https://www.sifest.it/it/si-fest-off/archivio-off.html | Q9: https://www.facebook.com/offsavignano/?locale=it_IT | R9: 2 | X9: 1
A10: FEST000051 | B10: Milano Photo Week | C10: Milano | D10: {=XLOOKUP(C10,Locations!A:A,Locations!D:D,"")} -> 6951411 | E10: {=XLOOKUP(C10,Locations!A:A,Locations!E:E,"")} -> Lombardia | F10: {=XLOOKUP(C10,Locations!A:A,Locations!F:F,"")} -> ITC4 | G10: IT | H10: 2017 | J10: 7 giorni | K10: annual | M10: https://bnl.it/it/Scopri-BNL/Partnership-ed-Eventi/Arte-e-Cultura/Mostre-Fotografiche/Milano-Photo-Week | Q10: https://www.facebook.com/milanophotoweek/?locale=it_IT | R10: 2 | X10: 1
A11: FEST000063 | B11: Artlab Eyeland | C11: Taranto | D11: {=XLOOKUP(C11,Locations!A:A,Locations!D:D,"")} -> 3165926 | E11: {=XLOOKUP(C11,Locations!A:A,Locations!E:E,"")} -> Puglia | F11: {=XLOOKUP(C11,Locations!A:A,Locations!F:F,"")} -> ITF4 | G11: IT | H11: 2023 | J11: 1 mese | K11: annual | L11: https://www.artlabeyeland.it/ | P11: https://www.instagram.com/artlab_eyeland/ | Q11: https://www.facebook.com/profile.php?id=100091904272457 | R11: 6 | X11: 1
A12: FEST000065 | B12: Ortigia Contemporanea | C12: Siracusa | D12: {=XLOOKUP(C12,Locations!A:A,Locations!D:D,"")} -> 2523083 | E12: {=XLOOKUP(C12,Locations!A:A,Locations!E:E,"")} -> Sicilia | F12: {=XLOOKUP(C12,Locations!A:A,Locations!F:F,"")} -> ITG1 | G12: IT | H12: 2024 | J12: 2 weekend | K12: annual | M12: https://www.arte.it/calendario-arte/siracusa/mostra-ortigia-contemporanea-i-festival-internazionale-d-arte-contemporanea-in-sicilia-97895 | P12: https://www.instagram.com/ortigiacontemporanea/ | Q12: https://www.facebook.com/ortigiacontemporanea/ | R12: 4 | X12: 1
A13: FEST000068 | B13: Arte Fiera | C13: Bologna | D13: {=XLOOKUP(C13,Locations!A:A,Locations!D:D,"")} -> 3181928 | E13: {=XLOOKUP(C13,Locations!A:A,Locations!E:E,"")} -> Emilia-Romagna | F13: {=XLOOKUP(C13,Locations!A:A,Locations!F:F,"")} -> ITH5 | G13: IT | H13: 1974 | J13: 3 giorni | K13: annual | L13: https://www.artefiera.it/home/776.html | P13: https://www.instagram.com/artefiera_bologna/ | Q13: http://www.facebook.com/artefiera/ | R13: 6 | X13: 1
A14: FEST000072 | B14: RoRegeneration | C14: Rovigo | D14: {=XLOOKUP(C14,Locations!A:A,Locations!D:D,"")} -> 3168843 | E14: {=XLOOKUP(C14,Locations!A:A,Locations!E:E,"")} -> Veneto | F14: {=XLOOKUP(C14,Locations!A:A,Locations!F:F,"")} -> ITH3 | G14: IT | H14: 2021 | J14: 7 giorni | K14: annual | M14: https://www.rovigoinfocitta.it/roregeneration-il-festival-della-rigenerazione-urbana-esplora-nuove-forme-d%E2%80%99arte/ | R14: 0 | X14: 1
A15: FEST000007 | B15: Contemporanea Film Festival | C15: Torino | D15: {=XLOOKUP(C15,Locations!A:A,Locations!D:D,"")} -> 8980539 | E15: {=XLOOKUP(C15,Locations!A:A,Locations!E:E,"")} -> Piemonte | F15: {=XLOOKUP(C15,Locations!A:A,Locations!F:F,"")} -> ITC1 | G15: IT | H15: 2022 | I15: active | J15: 5 | K15: annual | L15: https://www.contemporaneafilmfestival.com/ | N15: 1 | O15: IT_ONLY | P15: https://www.instagram.com/contemporanea_festival/ | Q15: https://www.facebook.com/ContemporaneaFilmFestival | R15: 8 | S15: non-profit | T15: 1 | W15: 1 | X15: 1 | Y15: 1 | Z15: 0 | AA15: 0 | AB15: 0 | AC15: 0 | AD15: 1 | AE15: mixed | AF15: mixed | AG15: 0
A16: FEST000010 | B16: Murgiafest | C16: Santeramo in Colle | D16: {=XLOOKUP(C16,Locations!A:A,Locations!D:D,"")} -> 3167327 | E16: {=XLOOKUP(C16,Locations!A:A,Locations!E:E,"")} -> Puglia | F16: {=XLOOKUP(C16,Locations!A:A,Locations!F:F,"")} -> ITF4 | G16: IT | H16: 2010 | I16: active | J16: 3 | K16: annual | M16: https://arcistandby.com/murgiafest-main/ | N16: 0 | O16: IT_ONLY | R16: 0 | S16: non-profit | T16: 0 | W16: 0 | X16: 1 | Y16: 1 | Z16: 0 | AA16: 0 | AB16: 0 | AC16: 1 | AD16: 1 | AE16: public_space | AF16: free | AG16: 1
A17: FEST000016 | B17: Alba e tramonto festival | C17: Castiglione d'Orcia | D17: {=XLOOKUP(C17,Locations!A:A,Locations!D:D,"")} -> 3179411 | E17: {=XLOOKUP(C17,Locations!A:A,Locations!E:E,"")} -> Toscana | F17: {=XLOOKUP(C17,Locations!A:A,Locations!F:F,"")} -> ITI1 | G17: IT | H17: 2020 | I17: active | J17: 15 | K17: annual | L17: https://www.albaetramontofestival.it/ | N17: 1 | O17: IT_ONLY | P17: https://www.instagram.com/albaetramontofestival/ | R17: 6 | S17: non-profit | T17: 1 | W17: 0 | X17: 1 | Y17: 1 | Z17: 1 | AA17: 1 | AB17: 1 | AC17: 1 | AD17: 0 | AE17: public_space | AF17: free | AG17: 1
A18: FEST000001 | B18: Xenos - Festival di performance | C18: Siena | D18: {=XLOOKUP(C18,Locations!A:A,Locations!D:D,"")} -> 3166548 | E18: {=XLOOKUP(C18,Locations!A:A,Locations!E:E,"")} -> Toscana | F18: {=XLOOKUP(C18,Locations!A:A,Locations!F:F,"")} -> ITI1 | G18: IT | H18: 2024 | I18: active | J18: 4 | K18: annual | L18: null | M18: https://www.santamariadellascala.com/eventi/xenos-festival-di-performance | N18: 0 | O18: MULTI | P18: null | Q18: null | R18: {=IF(A18:A1000="","",IF(L18:L1000<>"",2,0)+IF(N18:N1000=1,2,0)+IF(O18:O1000="IT_EN",1,0)+IF(O18:O1000="MULTI",2,0)+IF(P18:P1000<>"",2,0)+IF(Q18:Q1000<>"",2,0))} -> #REF! | S18: non-profit | T18: 1 | W18: 1 | X18: 1 | Y18: 1 | Z18: 0 | AA18: 1 | AB18: 0 | AC18: 1 | AD18: 1 | AE18: museum_gallery | AF18: mixed | AG18: 0
A19: FEST000022 | B19: Posidonia Green Festival | C19: Bogliasco | D19: {=XLOOKUP(C19,Locations!A:A,Locations!D:D,"")} -> 3181943 | E19: {=XLOOKUP(C19,Locations!A:A,Locations!E:E,"")} -> Liguria | F19: {=XLOOKUP(C19,Locations!A:A,Locations!F:F,"")} -> ITC3 | G19: IT | H19: 2008 | I19: active | J19: 2 | K19: annual | L19: https://posidoniagreenfestival.com/ | M19: null | N19: 1 | O19: MULTI | P19: https://www.instagram.com/posidoniagreenfestival/ | Q19: https://www.facebook.com/PosidoniaFestivalGreen/ | R19: 10 | S19: non-profit | T19: 0 | U19: 0 | V19: 1 | X19: 1 | Y19: 1 | Z19: 0 | AB19: 0 | AC19: 1 | AD19: 1 | AE19: public_space | AF19: free | AG19: 1 | AH19: In altre date si svolge anche a Barcellona.
A20: FEST000023 | B20: Sempre Più Fuori Festival | C20: Roma | D20: {=XLOOKUP(C20,Locations!A:A,Locations!D:D,"")} -> 8957247 | E20: {=XLOOKUP(C20,Locations!A:A,Locations!E:E,"")} -> Lazio | F20: {=XLOOKUP(C20,Locations!A:A,Locations!F:F,"")} -> ITI4 | G20: IT | H20: unknown | I20: active | J20: 12 | K20: annual | L20: https://www.semprepiufuori.it/ | M20: null | N20: 1 | O20: IT_ONLY | P20: https://www.instagram.com/semprepiufuori/ | Q20: https://www.facebook.com/semprepiufuorifestival | R20: 8 | S20: non-profit | T20: 1 | U20: 0 | V20: 1 | X20: 1 | Y20: 1 | Z20: 0 | AB20: 0 | AC20: 1 | AD20: 1 | AE20: mixed | AF20: mixed | AG20: 0
A21: FEST000019 | B21: Paradiso Film Fest | C21: Palazzo Adriano | D21: {=XLOOKUP(C21,Locations!A:A,Locations!D:D,"")} -> 2523925 | E21: {=XLOOKUP(C21,Locations!A:A,Locations!E:E,"")} -> Sicilia | F21: {=XLOOKUP(C21,Locations!A:A,Locations!F:F,"")} -> ITG1 | G21: IT | H21: 2020 | I21: active | J21: 3 | K21: annual | L21: https://www.paradisofilmfest.com/ | M21: null | N21: 1 | O21: IT_EN | P21: https://www.instagram.com/paradiso_film_fest/ | Q21: https://www.facebook.com/ParadisoFilmFest | R21: 9 | S21: non-profit | T21: 1 | W21: 1 | X21: 1 | Y21: 1 | Z21: 1 | AA21: 1 | AB21: 1 | AC21: 1 | AD21: 1 | AE21: 0 | AG21: 46227
A22: FEST000020 | B22: AESON Festival | C22: Fiumicello Villa Vicentina | D22: {=XLOOKUP(C22,Locations!A:A,Locations!D:D,"")} -> 12032187 | E22: {=XLOOKUP(C22,Locations!A:A,Locations!E:E,"")} -> Friuli-Venezia Giulia | F22: {=XLOOKUP(C22,Locations!A:A,Locations!F:F,"")} -> ITH4 | G22: IT | H22: 2008 | I22: active | J22: 4 | K22: annual | L22: https://www.aeson.it/ | M22: null | N22: 1 | O22: IT_ONLY | P22: https://www.instagram.com/aesonfestival/ | Q22: https://www.facebook.com/aeson.artinellanatura | R22: 8 | S22: non-profit | T22: 1 | W22: 1 | X22: 1 | Y22: 1 | Z22: 0 | AB22: 1 | AC22: 1 | AD22: 1 | AE22: public_space | AF22: free | AG22: 1 | AI22: 46227
